{"_id":{"$oid":"5d34a67a6b361d34247c1e41"},"hilo":{"$numberInt":"4"},"topico":{"$numberInt":"4"},"total_tweets":{"$numberInt":"3"},"total_retweets":{"$numberInt":"6267"},"total_favoritos":{"$numberInt":"15007"},"promedio_rt":{"$numberInt":"2089"},"promedio_fv":{"$numberInt":"5002"},"total_hashtags":{"$numberInt":"0"},"emocion_hilo_1":"Joy","tupla_emocion_hilo":"Joy+Surprise","user_total_followers":{"$numberInt":"263169"},"user_puntaje_sigmo":{"$numberDouble":"1.17499"},"user_verificado":true,"log_prt":{"$numberDouble":"3.3201462861110542"},"log_pfv":{"$numberDouble":"3.699230502883409"},"log_total_retweets":{"$numberDouble":"3.7971289877965524"},"log_total_favoritos":{"$numberDouble":"4.176322821034989"},"rnd_user_puntaje_sigmo":{"$numberDouble":"1.2"},"log_user_total_followers":{"$numberDouble":"5.420236380469888"}}
{"_id":{"$oid":"5d34a67a6b361d34247c1e42"},"hilo":{"$numberInt":"5"},"topico":{"$numberInt":"3"},"total_tweets":{"$numberInt":"4"},"total_retweets":{"$numberInt":"51"},"total_favoritos":{"$numberInt":"49"},"promedio_rt":{"$numberInt":"13"},"promedio_fv":{"$numberInt":"12"},"total_hashtags":{"$numberInt":"1"},"emocion_hilo_1":"Fear","tupla_emocion_hilo":"Fear+Disgust","user_total_followers":{"$numberInt":"6558"},"user_puntaje_sigmo":{"$numberDouble":"1.01279"},"user_verificado":false,"log_prt":{"$numberDouble":"1.146128035678238"},"log_pfv":{"$numberDouble":"1.1139433523068367"},"log_total_retweets":{"$numberDouble":"1.7160033436347992"},"log_total_favoritos":{"$numberDouble":"1.6989700043360187"},"rnd_user_puntaje_sigmo":{"$numberInt":"1"},"log_user_total_followers":{"$numberDouble":"3.816837630902035"}}
{"_id":{"$oid":"5d34a67a6b361d34247c1e43"},"hilo":{"$numberInt":"6"},"topico":{"$numberInt":"7"},"total_tweets":{"$numberInt":"4"},"total_retweets":{"$numberInt":"12068"},"total_favoritos":{"$numberInt":"21292"},"promedio_rt":{"$numberInt":"3017"},"promedio_fv":{"$numberInt":"5323"},"total_hashtags":{"$numberInt":"2"},"emocion_hilo_1":"Fear","tupla_emocion_hilo":"Fear+Sadness","user_total_followers":{"$numberInt":"74244"},"user_puntaje_sigmo":{"$numberDouble":"1.33755"},"user_verificado":true,"log_prt":{"$numberDouble":"3.479719235439571"},"log_pfv":{"$numberDouble":"3.7262380468026377"},"log_total_retweets":{"$numberDouble":"4.0816712872909235"},"log_total_favoritos":{"$numberDouble":"4.328236854094916"},"rnd_user_puntaje_sigmo":{"$numberDouble":"1.3"},"log_user_total_followers":{"$numberDouble":"4.870667211584855"}}
{"_id":{"$oid":"5d34a67a6b361d34247c1e44"},"hilo":{"$numberInt":"10"},"topico":{"$numberInt":"13"},"total_tweets":{"$numberInt":"4"},"total_retweets":{"$numberInt":"1489"},"total_favoritos":{"$numberInt":"1562"},"promedio_rt":{"$numberInt":"372"},"promedio_fv":{"$numberInt":"390"},"total_hashtags":{"$numberInt":"2"},"emocion_hilo_1":"Joy","tupla_emocion_hilo":"Joy+Fear","user_total_followers":{"$numberInt":"57367"},"user_puntaje_sigmo":{"$numberDouble":"1.81404"},"user_verificado":true,"log_prt":{"$numberDouble":"2.571708831808688"},"log_pfv":{"$numberDouble":"2.5921767573958667"},"log_total_retweets":{"$numberDouble":"3.173186268412274"},"log_total_favoritos":{"$numberDouble":"3.193958978019187"},"rnd_user_puntaje_sigmo":{"$numberDouble":"1.8"},"log_user_total_followers":{"$numberDouble":"4.758669709493661"}}
{"_id":{"$oid":"5d34a67a6b361d34247c1e45"},"hilo":{"$numberInt":"21"},"topico":{"$numberInt":"10"},"total_tweets":{"$numberInt":"5"},"total_retweets":{"$numberInt":"6500"},"total_favoritos":{"$numberInt":"8592"},"promedio_rt":{"$numberInt":"1300"},"promedio_fv":{"$numberInt":"1718"},"total_hashtags":{"$numberInt":"0"},"emocion_hilo_1":"Fear","tupla_emocion_hilo":"Fear+Joy","user_total_followers":{"$numberInt":"15067"},"user_puntaje_sigmo":{"$numberDouble":"1.04728"},"user_verificado":false,"log_prt":{"$numberDouble":"3.1142772965615864"},"log_pfv":{"$numberDouble":"3.2352758766870524"},"log_total_retweets":{"$numberDouble":"3.8129801660394804"},"log_total_favoritos":{"$numberDouble":"3.934144811792477"},"rnd_user_puntaje_sigmo":{"$numberInt":"1"},"log_user_total_followers":{"$numberDouble":"4.17805561153123"}}
{"_id":{"$oid":"5d34a67a6b361d34247c1e46"},"hilo":{"$numberInt":"23"},"topico":{"$numberInt":"2"},"total_tweets":{"$numberInt":"5"},"total_retweets":{"$numberInt":"321"},"total_favoritos":{"$numberInt":"348"},"promedio_rt":{"$numberInt":"64"},"promedio_fv":{"$numberInt":"70"},"total_hashtags":{"$numberInt":"4"},"emocion_hilo_1":"Fear","tupla_emocion_hilo":"Fear+Joy","user_total_followers":{"$numberInt":"44388"},"user_puntaje_sigmo":{"$numberDouble":"0.81818"},"user_verificado":false,"log_prt":{"$numberDouble":"1.8129133566428555"},"log_pfv":{"$numberDouble":"1.8512583487190752"},"log_total_retweets":{"$numberDouble":"2.507855871695831"},"log_total_favoritos":{"$numberDouble":"2.5428254269591797"},"rnd_user_puntaje_sigmo":{"$numberDouble":"0.8"},"log_user_total_followers":{"$numberDouble":"4.6472753613043984"}}
{"_id":{"$oid":"5d34a67a6b361d34247c1e47"},"hilo":{"$numberInt":"24"},"topico":{"$numberInt":"2"},"total_tweets":{"$numberInt":"5"},"total_retweets":{"$numberInt":"45568"},"total_favoritos":{"$numberInt":"117888"},"promedio_rt":{"$numberInt":"9114"},"promedio_fv":{"$numberInt":"23578"},"total_hashtags":{"$numberInt":"0"},"emocion_hilo_1":"Joy","tupla_emocion_hilo":"Joy+Anger","user_total_followers":{"$numberInt":"1914"},"user_puntaje_sigmo":{"$numberDouble":"0.82973"},"user_verificado":false,"log_prt":{"$numberDouble":"3.959756672990995"},"log_pfv":{"$numberDouble":"4.372525382451559"},"log_total_retweets":{"$numberDouble":"4.6586694982061685"},"log_total_favoritos":{"$numberDouble":"5.071473283787442"},"rnd_user_puntaje_sigmo":{"$numberDouble":"0.8"},"log_user_total_followers":{"$numberDouble":"3.2821687783046416"}}
{"_id":{"$oid":"5d34a67a6b361d34247c1e48"},"hilo":{"$numberInt":"27"},"topico":{"$numberInt":"10"},"total_tweets":{"$numberInt":"5"},"total_retweets":{"$numberInt":"199"},"total_favoritos":{"$numberInt":"172"},"promedio_rt":{"$numberInt":"40"},"promedio_fv":{"$numberInt":"34"},"total_hashtags":{"$numberInt":"0"},"emocion_hilo_1":"Joy","tupla_emocion_hilo":"Joy+Fear","user_total_followers":{"$numberInt":"4594"},"user_puntaje_sigmo":{"$numberDouble":"0.84691"},"user_verificado":false,"log_prt":{"$numberDouble":"1.6127838567197355"},"log_pfv":{"$numberDouble":"1.5440680443502757"},"log_total_retweets":{"$numberDouble":"2.3010299956639813"},"log_total_favoritos":{"$numberDouble":"2.2380461031287955"},"rnd_user_puntaje_sigmo":{"$numberDouble":"0.8"},"log_user_total_followers":{"$numberDouble":"3.66228551572213"}}
{"_id":{"$oid":"5d34a67a6b361d34247c1e49"},"hilo":{"$numberInt":"32"},"topico":{"$numberInt":"4"},"total_tweets":{"$numberInt":"5"},"total_retweets":{"$numberInt":"11454"},"total_favoritos":{"$numberInt":"34811"},"promedio_rt":{"$numberInt":"2291"},"promedio_fv":{"$numberInt":"6962"},"total_hashtags":{"$numberInt":"0"},"emocion_hilo_1":"Anger","tupla_emocion_hilo":"Anger+Joy","user_total_followers":{"$numberInt":"27485"},"user_puntaje_sigmo":{"$numberDouble":"1.00329"},"user_verificado":false,"log_prt":{"$numberDouble":"3.3602146132953523"},"log_pfv":{"$numberDouble":"3.84279639517558"},"log_total_retweets":{"$numberDouble":"4.058995093525416"},"log_total_favoritos":{"$numberDouble":"4.541728974850289"},"rnd_user_puntaje_sigmo":{"$numberInt":"1"},"log_user_total_followers":{"$numberDouble":"4.439111542159727"}}
{"_id":{"$oid":"5d34a67a6b361d34247c1e4a"},"hilo":{"$numberInt":"34"},"topico":{"$numberInt":"1"},"total_tweets":{"$numberInt":"5"},"total_retweets":{"$numberInt":"123"},"total_favoritos":{"$numberInt":"856"},"promedio_rt":{"$numberInt":"25"},"promedio_fv":{"$numberInt":"171"},"total_hashtags":{"$numberInt":"1"},"emocion_hilo_1":"Joy","tupla_emocion_hilo":"Joy+Fear","user_total_followers":{"$numberInt":"23229"},"user_puntaje_sigmo":{"$numberDouble":"1.25513"},"user_verificado":false,"log_prt":{"$numberDouble":"1.414973347970818"},"log_pfv":{"$numberDouble":"2.2355284469075487"},"log_total_retweets":{"$numberDouble":"2.093421685162235"},"log_total_favoritos":{"$numberDouble":"2.932980821923198"},"rnd_user_puntaje_sigmo":{"$numberDouble":"1.3"},"log_user_total_followers":{"$numberDouble":"4.366049209800235"}}
{"_id":{"$oid":"5d34a67a6b361d34247c1e4b"},"hilo":{"$numberInt":"35"},"topico":{"$numberInt":"4"},"total_tweets":{"$numberInt":"6"},"total_retweets":{"$numberInt":"37"},"total_favoritos":{"$numberInt":"193"},"promedio_rt":{"$numberInt":"6"},"promedio_fv":{"$numberInt":"32"},"total_hashtags":{"$numberInt":"0"},"emocion_hilo_1":"Anger","tupla_emocion_hilo":"Anger+Sadness","user_total_followers":{"$numberInt":"57688"},"user_puntaje_sigmo":{"$numberDouble":"1.03463"},"user_verificado":false,"log_prt":{"$numberDouble":"0.8450980400142568"},"log_pfv":{"$numberDouble":"1.5185139398778875"},"log_total_retweets":{"$numberDouble":"1.5797835966168101"},"log_total_favoritos":{"$numberDouble":"2.287801729930226"},"rnd_user_puntaje_sigmo":{"$numberInt":"1"},"log_user_total_followers":{"$numberDouble":"4.761093010820753"}}
{"_id":{"$oid":"5d34a67a6b361d34247c1e4c"},"hilo":{"$numberInt":"36"},"topico":{"$numberInt":"4"},"total_tweets":{"$numberInt":"6"},"total_retweets":{"$numberInt":"3382"},"total_favoritos":{"$numberInt":"7239"},"promedio_rt":{"$numberInt":"564"},"promedio_fv":{"$numberInt":"1206"},"total_hashtags":{"$numberInt":"0"},"emocion_hilo_1":"Sadness","tupla_emocion_hilo":"Sadness+Joy","user_total_followers":{"$numberInt":"578806"},"user_puntaje_sigmo":{"$numberDouble":"1.41355"},"user_verificado":true,"log_prt":{"$numberDouble":"2.7520484478194387"},"log_pfv":{"$numberDouble":"3.081707270097349"},"log_total_retweets":{"$numberDouble":"3.5293019977879805"},"log_total_favoritos":{"$numberDouble":"3.859738566197147"},"rnd_user_puntaje_sigmo":{"$numberDouble":"1.4"},"log_user_total_followers":{"$numberDouble":"5.762533774767301"}}
{"_id":{"$oid":"5d34a67a6b361d34247c1e4d"},"hilo":{"$numberInt":"40"},"topico":{"$numberInt":"4"},"total_tweets":{"$numberInt":"6"},"total_retweets":{"$numberInt":"7076"},"total_favoritos":{"$numberInt":"10524"},"promedio_rt":{"$numberInt":"1179"},"promedio_fv":{"$numberInt":"1754"},"total_hashtags":{"$numberInt":"1"},"emocion_hilo_1":"Joy","tupla_emocion_hilo":"Joy+Surprise","user_total_followers":{"$numberInt":"125031"},"user_puntaje_sigmo":{"$numberDouble":"1.27649"},"user_verificado":false,"log_prt":{"$numberDouble":"3.0718820073061255"},"log_pfv":{"$numberDouble":"3.244277120801843"},"log_total_retweets":{"$numberDouble":"3.849849195605258"},"log_total_favoritos":{"$numberDouble":"4.022222104507706"},"rnd_user_puntaje_sigmo":{"$numberDouble":"1.3"},"log_user_total_followers":{"$numberDouble":"5.09702117816689"}}
{"_id":{"$oid":"5d34a67a6b361d34247c1e4e"},"hilo":{"$numberInt":"41"},"topico":{"$numberInt":"3"},"total_tweets":{"$numberInt":"6"},"total_retweets":{"$numberInt":"150"},"total_favoritos":{"$numberInt":"531"},"promedio_rt":{"$numberInt":"25"},"promedio_fv":{"$numberInt":"88"},"total_hashtags":{"$numberInt":"0"},"emocion_hilo_1":"Joy","tupla_emocion_hilo":"Joy+Fear","user_total_followers":{"$numberInt":"15544"},"user_puntaje_sigmo":{"$numberDouble":"1.03829"},"user_verificado":false,"log_prt":{"$numberDouble":"1.414973347970818"},"log_pfv":{"$numberDouble":"1.9493900066449128"},"log_total_retweets":{"$numberDouble":"2.1789769472931693"},"log_total_favoritos":{"$numberDouble":"2.7259116322950483"},"rnd_user_puntaje_sigmo":{"$numberInt":"1"},"log_user_total_followers":{"$numberDouble":"4.191590726379211"}}
{"_id":{"$oid":"5d34a67a6b361d34247c1e4f"},"hilo":{"$numberInt":"42"},"topico":{"$numberInt":"4"},"total_tweets":{"$numberInt":"6"},"total_retweets":{"$numberInt":"144"},"total_favoritos":{"$numberInt":"194"},"promedio_rt":{"$numberInt":"24"},"promedio_fv":{"$numberInt":"32"},"total_hashtags":{"$numberInt":"0"},"emocion_hilo_1":"Joy","tupla_emocion_hilo":"Joy+Fear","user_total_followers":{"$numberInt":"45755"},"user_puntaje_sigmo":{"$numberDouble":"0.96577"},"user_verificado":true,"log_prt":{"$numberDouble":"1.3979400086720377"},"log_pfv":{"$numberDouble":"1.5185139398778875"},"log_total_retweets":{"$numberDouble":"2.161368002234975"},"log_total_favoritos":{"$numberDouble":"2.290034611362518"},"rnd_user_puntaje_sigmo":{"$numberInt":"1"},"log_user_total_followers":{"$numberDouble":"4.660448051321295"}}
{"_id":{"$oid":"5d34a67a6b361d34247c1e50"},"hilo":{"$numberInt":"44"},"topico":{"$numberInt":"7"},"total_tweets":{"$numberInt":"6"},"total_retweets":{"$numberInt":"2394"},"total_favoritos":{"$numberInt":"6216"},"promedio_rt":{"$numberInt":"399"},"promedio_fv":{"$numberInt":"1036"},"total_hashtags":{"$numberInt":"2"},"emocion_hilo_1":"Fear","tupla_emocion_hilo":"Fear+Joy","user_total_followers":{"$numberInt":"5403"},"user_puntaje_sigmo":{"$numberDouble":"0.84345"},"user_verificado":false,"log_prt":{"$numberDouble":"2.6020599913279625"},"log_pfv":{"$numberDouble":"3.015778756389041"},"log_total_retweets":{"$numberDouble":"3.379305517750582"},"log_total_favoritos":{"$numberDouble":"3.793580867368156"},"rnd_user_puntaje_sigmo":{"$numberDouble":"0.8"},"log_user_total_followers":{"$numberDouble":"3.732715340349993"}}
{"_id":{"$oid":"5d34a67a6b361d34247c1e51"},"hilo":{"$numberInt":"49"},"topico":{"$numberInt":"10"},"total_tweets":{"$numberInt":"6"},"total_retweets":{"$numberInt":"154"},"total_favoritos":{"$numberInt":"544"},"promedio_rt":{"$numberInt":"26"},"promedio_fv":{"$numberInt":"91"},"total_hashtags":{"$numberInt":"0"},"emocion_hilo_1":"Fear","tupla_emocion_hilo":"Fear+Joy","user_total_followers":{"$numberInt":"5885"},"user_puntaje_sigmo":{"$numberDouble":"0.91459"},"user_verificado":true,"log_prt":{"$numberDouble":"1.4313637641589874"},"log_pfv":{"$numberDouble":"1.9637878273455553"},"log_total_retweets":{"$numberDouble":"2.1903316981702914"},"log_total_favoritos":{"$numberDouble":"2.7363965022766426"},"rnd_user_puntaje_sigmo":{"$numberDouble":"0.9"},"log_user_total_followers":{"$numberDouble":"3.769820257763592"}}
{"_id":{"$oid":"5d34a67a6b361d34247c1e52"},"hilo":{"$numberInt":"54"},"topico":{"$numberInt":"4"},"total_tweets":{"$numberInt":"6"},"total_retweets":{"$numberInt":"155"},"total_favoritos":{"$numberInt":"87"},"promedio_rt":{"$numberInt":"26"},"promedio_fv":{"$numberInt":"14"},"total_hashtags":{"$numberInt":"1"},"emocion_hilo_1":"Fear","tupla_emocion_hilo":"Fear+Joy","user_total_followers":{"$numberInt":"3397"},"user_puntaje_sigmo":{"$numberDouble":"0.78883"},"user_verificado":false,"log_prt":{"$numberDouble":"1.4313637641589874"},"log_pfv":{"$numberDouble":"1.1760912590556813"},"log_total_retweets":{"$numberDouble":"2.1931245983544616"},"log_total_favoritos":{"$numberDouble":"1.9444826721501687"},"rnd_user_puntaje_sigmo":{"$numberDouble":"0.8"},"log_user_total_followers":{"$numberDouble":"3.5312233745330266"}}
{"_id":{"$oid":"5d34a67a6b361d34247c1e53"},"hilo":{"$numberInt":"59"},"topico":{"$numberInt":"4"},"total_tweets":{"$numberInt":"7"},"total_retweets":{"$numberInt":"619"},"total_favoritos":{"$numberInt":"4188"},"promedio_rt":{"$numberInt":"88"},"promedio_fv":{"$numberInt":"598"},"total_hashtags":{"$numberInt":"0"},"emocion_hilo_1":"Joy","tupla_emocion_hilo":"Joy+Fear","user_total_followers":{"$numberInt":"78895"},"user_puntaje_sigmo":{"$numberDouble":"1.1925"},"user_verificado":true,"log_prt":{"$numberDouble":"1.9493900066449128"},"log_pfv":{"$numberDouble":"2.7774268223893115"},"log_total_retweets":{"$numberDouble":"2.792391689498254"},"log_total_favoritos":{"$numberDouble":"3.6221103603612197"},"rnd_user_puntaje_sigmo":{"$numberDouble":"1.2"},"log_user_total_followers":{"$numberDouble":"4.897054985187062"}}
{"_id":{"$oid":"5d34a67a6b361d34247c1e54"},"hilo":{"$numberInt":"63"},"topico":{"$numberInt":"2"},"total_tweets":{"$numberInt":"7"},"total_retweets":{"$numberInt":"88"},"total_favoritos":{"$numberInt":"276"},"promedio_rt":{"$numberInt":"13"},"promedio_fv":{"$numberInt":"39"},"total_hashtags":{"$numberInt":"5"},"emocion_hilo_1":"Fear","tupla_emocion_hilo":"Fear+Anger","user_total_followers":{"$numberInt":"697"},"user_puntaje_sigmo":{"$numberDouble":"0.75171"},"user_verificado":false,"log_prt":{"$numberDouble":"1.146128035678238"},"log_pfv":{"$numberDouble":"1.6020599913279623"},"log_total_retweets":{"$numberDouble":"1.9493900066449128"},"log_total_favoritos":{"$numberDouble":"2.4424797690644486"},"rnd_user_puntaje_sigmo":{"$numberDouble":"0.8"},"log_user_total_followers":{"$numberDouble":"2.843855422623161"}}
{"_id":{"$oid":"5d34a67a6b361d34247c1e55"},"hilo":{"$numberInt":"65"},"topico":{"$numberInt":"7"},"total_tweets":{"$numberInt":"7"},"total_retweets":{"$numberInt":"2403"},"total_favoritos":{"$numberInt":"5278"},"promedio_rt":{"$numberInt":"343"},"promedio_fv":{"$numberInt":"754"},"total_hashtags":{"$numberInt":"0"},"emocion_hilo_1":"Joy","tupla_emocion_hilo":"Joy+Fear","user_total_followers":{"$numberInt":"9356"},"user_puntaje_sigmo":{"$numberDouble":"0.79609"},"user_verificado":false,"log_prt":{"$numberDouble":"2.53655844257153"},"log_pfv":{"$numberDouble":"2.8779469516291885"},"log_total_retweets":{"$numberDouble":"3.380934463330702"},"log_total_favoritos":{"$numberDouble":"3.7225516620009587"},"rnd_user_puntaje_sigmo":{"$numberDouble":"0.8"},"log_user_total_followers":{"$numberDouble":"3.9711366294768062"}}
{"_id":{"$oid":"5d34a67a6b361d34247c1e56"},"hilo":{"$numberInt":"66"},"topico":{"$numberInt":"4"},"total_tweets":{"$numberInt":"7"},"total_retweets":{"$numberInt":"1128"},"total_favoritos":{"$numberInt":"2132"},"promedio_rt":{"$numberInt":"161"},"promedio_fv":{"$numberInt":"305"},"total_hashtags":{"$numberInt":"1"},"emocion_hilo_1":"Joy","tupla_emocion_hilo":"Joy+Fear","user_total_followers":{"$numberInt":"41560"},"user_puntaje_sigmo":{"$numberDouble":"0.86444"},"user_verificado":false,"log_prt":{"$numberDouble":"2.2095150145426308"},"log_pfv":{"$numberDouble":"2.48572142648158"},"log_total_retweets":{"$numberDouble":"3.052693941924968"},"log_total_favoritos":{"$numberDouble":"3.3289908554494287"},"rnd_user_puntaje_sigmo":{"$numberDouble":"0.9"},"log_user_total_followers":{"$numberDouble":"4.618685988578525"}}
{"_id":{"$oid":"5d34a67a6b361d34247c1e57"},"hilo":{"$numberInt":"72"},"topico":{"$numberInt":"5"},"total_tweets":{"$numberInt":"7"},"total_retweets":{"$numberInt":"1693"},"total_favoritos":{"$numberInt":"5282"},"promedio_rt":{"$numberInt":"242"},"promedio_fv":{"$numberInt":"755"},"total_hashtags":{"$numberInt":"0"},"emocion_hilo_1":"Joy","tupla_emocion_hilo":"Joy+Surprise","user_total_followers":{"$numberInt":"194060"},"user_puntaje_sigmo":{"$numberDouble":"1.31103"},"user_verificado":false,"log_prt":{"$numberDouble":"2.385606273598312"},"log_pfv":{"$numberDouble":"2.8785217955012063"},"log_total_retweets":{"$numberDouble":"3.228913405994688"},"log_total_favoritos":{"$numberDouble":"3.722880610686939"},"rnd_user_puntaje_sigmo":{"$numberDouble":"1.3"},"log_user_total_followers":{"$numberDouble":"5.28793826497814"}}
{"_id":{"$oid":"5d34a67a6b361d34247c1e58"},"hilo":{"$numberInt":"73"},"topico":{"$numberInt":"4"},"total_tweets":{"$numberInt":"7"},"total_retweets":{"$numberInt":"58"},"total_favoritos":{"$numberInt":"230"},"promedio_rt":{"$numberInt":"8"},"promedio_fv":{"$numberInt":"33"},"total_hashtags":{"$numberInt":"0"},"emocion_hilo_1":"Fear","tupla_emocion_hilo":"Fear+Joy","user_total_followers":{"$numberInt":"11726"},"user_puntaje_sigmo":{"$numberDouble":"1.02932"},"user_verificado":true,"log_prt":{"$numberDouble":"0.9542425094393249"},"log_pfv":{"$numberDouble":"1.5314789170422551"},"log_total_retweets":{"$numberDouble":"1.7708520116421442"},"log_total_favoritos":{"$numberDouble":"2.3636119798921444"},"rnd_user_puntaje_sigmo":{"$numberInt":"1"},"log_user_total_followers":{"$numberDouble":"4.06918692515191"}}
{"_id":{"$oid":"5d34a67a6b361d34247c1e59"},"hilo":{"$numberInt":"76"},"topico":{"$numberInt":"9"},"total_tweets":{"$numberInt":"8"},"total_retweets":{"$numberInt":"26698"},"total_favoritos":{"$numberInt":"118591"},"promedio_rt":{"$numberInt":"3337"},"promedio_fv":{"$numberInt":"14824"},"total_hashtags":{"$numberInt":"0"},"emocion_hilo_1":"Joy","tupla_emocion_hilo":"Joy+Surprise","user_total_followers":{"$numberInt":"2777455"},"user_puntaje_sigmo":{"$numberDouble":"1.82529"},"user_verificado":true,"log_prt":{"$numberDouble":"3.5234863323432277"},"log_pfv":{"$numberDouble":"4.1709947020363005"},"log_total_retweets":{"$numberDouble":"4.426494995349033"},"log_total_favoritos":{"$numberDouble":"5.0740553933027845"},"rnd_user_puntaje_sigmo":{"$numberDouble":"1.8"},"log_user_total_followers":{"$numberDouble":"6.4436471876458254"}}
{"_id":{"$oid":"5d34a67a6b361d34247c1e5a"},"hilo":{"$numberInt":"77"},"topico":{"$numberInt":"12"},"total_tweets":{"$numberInt":"8"},"total_retweets":{"$numberInt":"174"},"total_favoritos":{"$numberInt":"1048"},"promedio_rt":{"$numberInt":"22"},"promedio_fv":{"$numberInt":"131"},"total_hashtags":{"$numberInt":"0"},"emocion_hilo_1":"Surprise","tupla_emocion_hilo":"Surprise+Joy","user_total_followers":{"$numberInt":"1545"},"user_puntaje_sigmo":{"$numberDouble":"0.88354"},"user_verificado":false,"log_prt":{"$numberDouble":"1.3617278360175928"},"log_pfv":{"$numberDouble":"2.12057393120585"},"log_total_retweets":{"$numberDouble":"2.2430380486862944"},"log_total_favoritos":{"$numberDouble":"3.020775488193558"},"rnd_user_puntaje_sigmo":{"$numberDouble":"0.9"},"log_user_total_followers":{"$numberDouble":"3.189209489582306"}}
{"_id":{"$oid":"5d34a67a6b361d34247c1e5b"},"hilo":{"$numberInt":"83"},"topico":{"$numberInt":"10"},"total_tweets":{"$numberInt":"8"},"total_retweets":{"$numberInt":"1185"},"total_favoritos":{"$numberInt":"5110"},"promedio_rt":{"$numberInt":"148"},"promedio_fv":{"$numberInt":"639"},"total_hashtags":{"$numberInt":"0"},"emocion_hilo_1":"Joy","tupla_emocion_hilo":"Joy+Fear","user_total_followers":{"$numberInt":"12396"},"user_puntaje_sigmo":{"$numberDouble":"0.8396"},"user_verificado":false,"log_prt":{"$numberDouble":"2.173186268412274"},"log_pfv":{"$numberDouble":"2.806179973983887"},"log_total_retweets":{"$numberDouble":"3.074084689028244"},"log_total_favoritos":{"$numberDouble":"3.708505880955237"},"rnd_user_puntaje_sigmo":{"$numberDouble":"0.8"},"log_user_total_followers":{"$numberDouble":"4.093316601204331"}}
{"_id":{"$oid":"5d34a67a6b361d34247c1e5c"},"hilo":{"$numberInt":"86"},"topico":{"$numberInt":"3"},"total_tweets":{"$numberInt":"8"},"total_retweets":{"$numberInt":"21340"},"total_favoritos":{"$numberInt":"39383"},"promedio_rt":{"$numberInt":"2668"},"promedio_fv":{"$numberInt":"4923"},"total_hashtags":{"$numberInt":"1"},"emocion_hilo_1":"Joy","tupla_emocion_hilo":"Joy+Fear","user_total_followers":{"$numberInt":"22749"},"user_puntaje_sigmo":{"$numberDouble":"0.91411"},"user_verificado":true,"log_prt":{"$numberDouble":"3.4263485737875077"},"log_pfv":{"$numberDouble":"3.6923180442592787"},"log_total_retweets":{"$numberDouble":"4.329214765805725"},"log_total_favoritos":{"$numberDouble":"4.595319822764699"},"rnd_user_puntaje_sigmo":{"$numberDouble":"0.9"},"log_user_total_followers":{"$numberDouble":"4.356981400993131"}}
{"_id":{"$oid":"5d34a67a6b361d34247c1e5d"},"hilo":{"$numberInt":"89"},"topico":{"$numberInt":"4"},"total_tweets":{"$numberInt":"8"},"total_retweets":{"$numberInt":"29572"},"total_favoritos":{"$numberInt":"94052"},"promedio_rt":{"$numberInt":"3696"},"promedio_fv":{"$numberInt":"11756"},"total_hashtags":{"$numberInt":"1"},"emocion_hilo_1":"Joy","tupla_emocion_hilo":"Joy+Anger","user_total_followers":{"$numberInt":"271068"},"user_puntaje_sigmo":{"$numberDouble":"1.48879"},"user_verificado":true,"log_prt":{"$numberDouble":"3.5678494505731067"},"log_pfv":{"$numberDouble":"4.070296518197765"},"log_total_retweets":{"$numberDouble":"4.470895383280216"},"log_total_favoritos":{"$numberDouble":"4.973372652758981"},"rnd_user_puntaje_sigmo":{"$numberDouble":"1.5"},"log_user_total_followers":{"$numberDouble":"5.433079853623477"}}
{"_id":{"$oid":"5d34a67a6b361d34247c1e5e"},"hilo":{"$numberInt":"92"},"topico":{"$numberInt":"13"},"total_tweets":{"$numberInt":"8"},"total_retweets":{"$numberInt":"1210"},"total_favoritos":{"$numberInt":"3499"},"promedio_rt":{"$numberInt":"151"},"promedio_fv":{"$numberInt":"437"},"total_hashtags":{"$numberInt":"0"},"emocion_hilo_1":"Fear","tupla_emocion_hilo":"Fear+Disgust","user_total_followers":{"$numberInt":"44233"},"user_puntaje_sigmo":{"$numberDouble":"1.86475"},"user_verificado":false,"log_prt":{"$numberDouble":"2.1818435879447726"},"log_pfv":{"$numberDouble":"2.6414741105040997"},"log_total_retweets":{"$numberDouble":"3.0831441431430524"},"log_total_favoritos":{"$numberDouble":"3.5440680443502757"},"rnd_user_puntaje_sigmo":{"$numberDouble":"1.9"},"log_user_total_followers":{"$numberDouble":"4.645756213603842"}}
{"_id":{"$oid":"5d34a67a6b361d34247c1e5f"},"hilo":{"$numberInt":"97"},"topico":{"$numberInt":"9"},"total_tweets":{"$numberInt":"9"},"total_retweets":{"$numberInt":"385"},"total_favoritos":{"$numberInt":"990"},"promedio_rt":{"$numberInt":"43"},"promedio_fv":{"$numberInt":"110"},"total_hashtags":{"$numberInt":"0"},"emocion_hilo_1":"Joy","tupla_emocion_hilo":"Joy+Fear","user_total_followers":{"$numberInt":"51265"},"user_puntaje_sigmo":{"$numberDouble":"1.04661"},"user_verificado":false,"log_prt":{"$numberDouble":"1.6434526764861874"},"log_pfv":{"$numberDouble":"2.0453229787866576"},"log_total_retweets":{"$numberDouble":"2.586587304671755"},"log_total_favoritos":{"$numberDouble":"2.9960736544852753"},"rnd_user_puntaje_sigmo":{"$numberInt":"1"},"log_user_total_followers":{"$numberDouble":"4.709829433186508"}}
{"_id":{"$oid":"5d34a67a6b361d34247c1e60"},"hilo":{"$numberInt":"98"},"topico":{"$numberInt":"4"},"total_tweets":{"$numberInt":"9"},"total_retweets":{"$numberInt":"833"},"total_favoritos":{"$numberInt":"4640"},"promedio_rt":{"$numberInt":"93"},"promedio_fv":{"$numberInt":"516"},"total_hashtags":{"$numberInt":"0"},"emocion_hilo_1":"Joy","tupla_emocion_hilo":"Joy+Surprise","user_total_followers":{"$numberInt":"461907"},"user_puntaje_sigmo":{"$numberDouble":"1.49786"},"user_verificado":true,"log_prt":{"$numberDouble":"1.9731278535996986"},"log_pfv":{"$numberDouble":"2.7134905430939424"},"log_total_retweets":{"$numberDouble":"2.921166050637739"},"log_total_favoritos":{"$numberDouble":"3.66661156841903"},"rnd_user_puntaje_sigmo":{"$numberDouble":"1.5"},"log_user_total_followers":{"$numberDouble":"5.66455548406029"}}
{"_id":{"$oid":"5d34a67a6b361d34247c1e61"},"hilo":{"$numberInt":"101"},"topico":{"$numberInt":"4"},"total_tweets":{"$numberInt":"9"},"total_retweets":{"$numberInt":"93"},"total_favoritos":{"$numberInt":"241"},"promedio_rt":{"$numberInt":"10"},"promedio_fv":{"$numberInt":"27"},"total_hashtags":{"$numberInt":"0"},"emocion_hilo_1":"Fear","tupla_emocion_hilo":"Fear+Joy","user_total_followers":{"$numberInt":"1579"},"user_puntaje_sigmo":{"$numberDouble":"0.80668"},"user_verificado":false,"log_prt":{"$numberDouble":"1.0413926851582251"},"log_pfv":{"$numberDouble":"1.4471580313422192"},"log_total_retweets":{"$numberDouble":"1.9731278535996986"},"log_total_favoritos":{"$numberDouble":"2.383815365980431"},"rnd_user_puntaje_sigmo":{"$numberDouble":"0.8"},"log_user_total_followers":{"$numberDouble":"3.1986570869544226"}}
{"_id":{"$oid":"5d34a67a6b361d34247c1e62"},"hilo":{"$numberInt":"102"},"topico":{"$numberInt":"4"},"total_tweets":{"$numberInt":"9"},"total_retweets":{"$numberInt":"296"},"total_favoritos":{"$numberInt":"1452"},"promedio_rt":{"$numberInt":"33"},"promedio_fv":{"$numberInt":"161"},"total_hashtags":{"$numberInt":"2"},"emocion_hilo_1":"Fear","tupla_emocion_hilo":"Fear+Joy","user_total_followers":{"$numberInt":"2919"},"user_puntaje_sigmo":{"$numberDouble":"0.74127"},"user_verificado":false,"log_prt":{"$numberDouble":"1.5314789170422551"},"log_pfv":{"$numberDouble":"2.2095150145426308"},"log_total_retweets":{"$numberDouble":"2.4727564493172123"},"log_total_favoritos":{"$numberDouble":"3.1622656142980214"},"rnd_user_puntaje_sigmo":{"$numberDouble":"0.7"},"log_user_total_followers":{"$numberDouble":"3.4653828514484184"}}
{"_id":{"$oid":"5d34a67a6b361d34247c1e63"},"hilo":{"$numberInt":"111"},"topico":{"$numberInt":"5"},"total_tweets":{"$numberInt":"9"},"total_retweets":{"$numberInt":"61"},"total_favoritos":{"$numberInt":"194"},"promedio_rt":{"$numberInt":"7"},"promedio_fv":{"$numberInt":"22"},"total_hashtags":{"$numberInt":"1"},"emocion_hilo_1":"Fear","tupla_emocion_hilo":"Fear+Joy","user_total_followers":{"$numberInt":"6354"},"user_puntaje_sigmo":{"$numberDouble":"1.10526"},"user_verificado":false,"log_prt":{"$numberDouble":"0.9030899869919435"},"log_pfv":{"$numberDouble":"1.3617278360175928"},"log_total_retweets":{"$numberDouble":"1.792391689498254"},"log_total_favoritos":{"$numberDouble":"2.290034611362518"},"rnd_user_puntaje_sigmo":{"$numberDouble":"1.1"},"log_user_total_followers":{"$numberDouble":"3.803115554890027"}}
{"_id":{"$oid":"5d34a67a6b361d34247c1e64"},"hilo":{"$numberInt":"112"},"topico":{"$numberInt":"3"},"total_tweets":{"$numberInt":"9"},"total_retweets":{"$numberInt":"7999"},"total_favoritos":{"$numberInt":"14214"},"promedio_rt":{"$numberInt":"889"},"promedio_fv":{"$numberInt":"1579"},"total_hashtags":{"$numberInt":"0"},"emocion_hilo_1":"Joy","tupla_emocion_hilo":"Joy+Fear","user_total_followers":{"$numberInt":"18540"},"user_puntaje_sigmo":{"$numberDouble":"1.42688"},"user_verificado":false,"log_prt":{"$numberDouble":"2.949390006644913"},"log_pfv":{"$numberDouble":"3.1986570869544226"},"log_total_retweets":{"$numberDouble":"3.9030899869919438"},"log_total_favoritos":{"$numberDouble":"4.152746864026461"},"rnd_user_puntaje_sigmo":{"$numberDouble":"1.4"},"log_user_total_followers":{"$numberDouble":"4.268133153906103"}}
{"_id":{"$oid":"5d34a67a6b361d34247c1e65"},"hilo":{"$numberInt":"120"},"topico":{"$numberInt":"4"},"total_tweets":{"$numberInt":"9"},"total_retweets":{"$numberInt":"5770"},"total_favoritos":{"$numberInt":"12967"},"promedio_rt":{"$numberInt":"641"},"promedio_fv":{"$numberInt":"1441"},"total_hashtags":{"$numberInt":"0"},"emocion_hilo_1":"Joy","tupla_emocion_hilo":"Joy+Fear","user_total_followers":{"$numberInt":"70609"},"user_puntaje_sigmo":{"$numberDouble":"1.20683"},"user_verificado":true,"log_prt":{"$numberDouble":"2.807535028068853"},"log_pfv":{"$numberDouble":"3.15896526038341"},"log_total_retweets":{"$numberDouble":"3.761251074308663"},"log_total_favoritos":{"$numberDouble":"4.112873001840459"},"rnd_user_puntaje_sigmo":{"$numberDouble":"1.2"},"log_user_total_followers":{"$numberDouble":"4.848866211494779"}}
{"_id":{"$oid":"5d34a67a6b361d34247c1e66"},"hilo":{"$numberInt":"121"},"topico":{"$numberInt":"0"},"total_tweets":{"$numberInt":"9"},"total_retweets":{"$numberInt":"146"},"total_favoritos":{"$numberInt":"1415"},"promedio_rt":{"$numberInt":"16"},"promedio_fv":{"$numberInt":"157"},"total_hashtags":{"$numberInt":"1"},"emocion_hilo_1":"Joy","tupla_emocion_hilo":"Joy+Fear","user_total_followers":{"$numberInt":"23229"},"user_puntaje_sigmo":{"$numberDouble":"1.25513"},"user_verificado":false,"log_prt":{"$numberDouble":"1.2304489213782739"},"log_pfv":{"$numberDouble":"2.1986570869544226"},"log_total_retweets":{"$numberDouble":"2.167317334748176"},"log_total_favoritos":{"$numberDouble":"3.15106325335375"},"rnd_user_puntaje_sigmo":{"$numberDouble":"1.3"},"log_user_total_followers":{"$numberDouble":"4.366049209800235"}}
{"_id":{"$oid":"5d34a67a6b361d34247c1e67"},"hilo":{"$numberInt":"122"},"topico":{"$numberInt":"12"},"total_tweets":{"$numberInt":"10"},"total_retweets":{"$numberInt":"197"},"total_favoritos":{"$numberInt":"525"},"promedio_rt":{"$numberInt":"20"},"promedio_fv":{"$numberInt":"52"},"total_hashtags":{"$numberInt":"0"},"emocion_hilo_1":"Joy","tupla_emocion_hilo":"Joy+Fear","user_total_followers":{"$numberInt":"682"},"user_puntaje_sigmo":{"$numberDouble":"0.80005"},"user_verificado":false,"log_prt":{"$numberDouble":"1.3222192947339193"},"log_pfv":{"$numberDouble":"1.724275869600789"},"log_total_retweets":{"$numberDouble":"2.296665190261531"},"log_total_favoritos":{"$numberDouble":"2.7209857441537393"},"rnd_user_puntaje_sigmo":{"$numberDouble":"0.8"},"log_user_total_followers":{"$numberDouble":"2.8344207036815328"}}
{"_id":{"$oid":"5d34a67a6b361d34247c1e68"},"hilo":{"$numberInt":"123"},"topico":{"$numberInt":"5"},"total_tweets":{"$numberInt":"10"},"total_retweets":{"$numberInt":"318"},"total_favoritos":{"$numberInt":"417"},"promedio_rt":{"$numberInt":"32"},"promedio_fv":{"$numberInt":"42"},"total_hashtags":{"$numberInt":"0"},"emocion_hilo_1":"Joy","tupla_emocion_hilo":"Joy+Fear","user_total_followers":{"$numberInt":"22831"},"user_puntaje_sigmo":{"$numberDouble":"0.98163"},"user_verificado":false,"log_prt":{"$numberDouble":"1.5185139398778875"},"log_pfv":{"$numberDouble":"1.6334684555795864"},"log_total_retweets":{"$numberDouble":"2.503790683057181"},"log_total_favoritos":{"$numberDouble":"2.621176281775035"},"rnd_user_puntaje_sigmo":{"$numberInt":"1"},"log_user_total_followers":{"$numberDouble":"4.358543955770572"}}
{"_id":{"$oid":"5d34a67a6b361d34247c1e69"},"hilo":{"$numberInt":"126"},"topico":{"$numberInt":"4"},"total_tweets":{"$numberInt":"10"},"total_retweets":{"$numberInt":"395"},"total_favoritos":{"$numberInt":"1717"},"promedio_rt":{"$numberInt":"40"},"promedio_fv":{"$numberInt":"172"},"total_hashtags":{"$numberInt":"0"},"emocion_hilo_1":"Joy","tupla_emocion_hilo":"Joy+Sadness","user_total_followers":{"$numberInt":"5754"},"user_puntaje_sigmo":{"$numberDouble":"0.86429"},"user_verificado":false,"log_prt":{"$numberDouble":"1.6127838567197355"},"log_pfv":{"$numberDouble":"2.2380461031287955"},"log_total_retweets":{"$numberDouble":"2.597695185925512"},"log_total_favoritos":{"$numberDouble":"3.2350231594952237"},"rnd_user_puntaje_sigmo":{"$numberDouble":"0.9"},"log_user_total_followers":{"$numberDouble":"3.760045327965811"}}
{"_id":{"$oid":"5d34a67a6b361d34247c1e6a"},"hilo":{"$numberInt":"127"},"topico":{"$numberInt":"7"},"total_tweets":{"$numberInt":"10"},"total_retweets":{"$numberInt":"13635"},"total_favoritos":{"$numberInt":"52458"},"promedio_rt":{"$numberInt":"1364"},"promedio_fv":{"$numberInt":"5246"},"total_hashtags":{"$numberInt":"0"},"emocion_hilo_1":"Disgust","tupla_emocion_hilo":"Disgust+Joy","user_total_followers":{"$numberInt":"63504"},"user_puntaje_sigmo":{"$numberDouble":"1.20577"},"user_verificado":true,"log_prt":{"$numberDouble":"3.1351326513767748"},"log_pfv":{"$numberDouble":"3.719911064198339"},"log_total_retweets":{"$numberDouble":"4.134686992556854"},"log_total_favoritos":{"$numberDouble":"4.719820007592092"},"rnd_user_puntaje_sigmo":{"$numberDouble":"1.2"},"log_user_total_followers":{"$numberDouble":"4.802807920361628"}}
{"_id":{"$oid":"5d34a67a6b361d34247c1e6b"},"hilo":{"$numberInt":"130"},"topico":{"$numberInt":"9"},"total_tweets":{"$numberInt":"10"},"total_retweets":{"$numberInt":"125"},"total_favoritos":{"$numberInt":"428"},"promedio_rt":{"$numberInt":"12"},"promedio_fv":{"$numberInt":"43"},"total_hashtags":{"$numberInt":"3"},"emocion_hilo_1":"Fear","tupla_emocion_hilo":"Fear+Sadness","user_total_followers":{"$numberInt":"58433"},"user_puntaje_sigmo":{"$numberDouble":"1.36473"},"user_verificado":false,"log_prt":{"$numberDouble":"1.1139433523068367"},"log_pfv":{"$numberDouble":"1.6434526764861874"},"log_total_retweets":{"$numberDouble":"2.100370545117563"},"log_total_favoritos":{"$numberDouble":"2.6324572921847245"},"rnd_user_puntaje_sigmo":{"$numberDouble":"1.4"},"log_user_total_followers":{"$numberDouble":"4.76666561621731"}}
{"_id":{"$oid":"5d34a67a6b361d34247c1e6c"},"hilo":{"$numberInt":"135"},"topico":{"$numberInt":"9"},"total_tweets":{"$numberInt":"10"},"total_retweets":{"$numberInt":"31638"},"total_favoritos":{"$numberInt":"75299"},"promedio_rt":{"$numberInt":"3164"},"promedio_fv":{"$numberInt":"7530"},"total_hashtags":{"$numberInt":"0"},"emocion_hilo_1":"Fear","tupla_emocion_hilo":"Fear+Surprise","user_total_followers":{"$numberInt":"9639982"},"user_puntaje_sigmo":{"$numberDouble":"1.54606"},"user_verificado":true,"log_prt":{"$numberDouble":"3.500373714353374"},"log_pfv":{"$numberDouble":"3.8768526476013436"},"log_total_retweets":{"$numberDouble":"4.500222748487298"},"log_total_favoritos":{"$numberDouble":"4.876794976200701"},"rnd_user_puntaje_sigmo":{"$numberDouble":"1.5"},"log_user_total_followers":{"$numberDouble":"6.984076268030144"}}
{"_id":{"$oid":"5d34a67a6b361d34247c1e6d"},"hilo":{"$numberInt":"141"},"topico":{"$numberInt":"2"},"total_tweets":{"$numberInt":"11"},"total_retweets":{"$numberInt":"47395"},"total_favoritos":{"$numberInt":"143072"},"promedio_rt":{"$numberInt":"4309"},"promedio_fv":{"$numberInt":"13007"},"total_hashtags":{"$numberInt":"0"},"emocion_hilo_1":"Anger","tupla_emocion_hilo":"Anger+Joy","user_total_followers":{"$numberInt":"77630"},"user_puntaje_sigmo":{"$numberDouble":"1.16824"},"user_verificado":true,"log_prt":{"$numberDouble":"3.6344772701607315"},"log_pfv":{"$numberDouble":"4.114210528249993"},"log_total_retweets":{"$numberDouble":"4.675741690804246"},"log_total_favoritos":{"$numberDouble":"5.155557683673317"},"rnd_user_puntaje_sigmo":{"$numberDouble":"1.2"},"log_user_total_followers":{"$numberDouble":"4.89003518054297"}}
{"_id":{"$oid":"5d34a67a6b361d34247c1e6e"},"hilo":{"$numberInt":"142"},"topico":{"$numberInt":"4"},"total_tweets":{"$numberInt":"11"},"total_retweets":{"$numberInt":"88155"},"total_favoritos":{"$numberInt":"395028"},"promedio_rt":{"$numberInt":"8014"},"promedio_fv":{"$numberInt":"35912"},"total_hashtags":{"$numberInt":"0"},"emocion_hilo_1":"Anger","tupla_emocion_hilo":"Anger+Joy","user_total_followers":{"$numberInt":"24529"},"user_puntaje_sigmo":{"$numberDouble":"1.05525"},"user_verificado":true,"log_prt":{"$numberDouble":"3.9039035266901636"},"log_pfv":{"$numberDouble":"4.555251685522227"},"log_total_retweets":{"$numberDouble":"4.94525187622937"},"log_total_favoritos":{"$numberDouble":"5.596628979367388"},"rnd_user_puntaje_sigmo":{"$numberDouble":"1.1"},"log_user_total_followers":{"$numberDouble":"4.389697548206386"}}
{"_id":{"$oid":"5d34a67a6b361d34247c1e6f"},"hilo":{"$numberInt":"145"},"topico":{"$numberInt":"4"},"total_tweets":{"$numberInt":"11"},"total_retweets":{"$numberInt":"3572"},"total_favoritos":{"$numberInt":"13595"},"promedio_rt":{"$numberInt":"325"},"promedio_fv":{"$numberInt":"1236"},"total_hashtags":{"$numberInt":"0"},"emocion_hilo_1":"Joy","tupla_emocion_hilo":"Joy+Fear","user_total_followers":{"$numberInt":"129526"},"user_puntaje_sigmo":{"$numberDouble":"1.15359"},"user_verificado":true,"log_prt":{"$numberDouble":"2.513217600067939"},"log_pfv":{"$numberDouble":"3.0923696996291206"},"log_total_retweets":{"$numberDouble":"3.55303301620244"},"log_total_favoritos":{"$numberDouble":"4.1334111559110225"},"rnd_user_puntaje_sigmo":{"$numberDouble":"1.2"},"log_user_total_followers":{"$numberDouble":"5.1123603068634855"}}
{"_id":{"$oid":"5d34a67a6b361d34247c1e70"},"hilo":{"$numberInt":"152"},"topico":{"$numberInt":"1"},"total_tweets":{"$numberInt":"11"},"total_retweets":{"$numberInt":"2001"},"total_favoritos":{"$numberInt":"8669"},"promedio_rt":{"$numberInt":"182"},"promedio_fv":{"$numberInt":"788"},"total_hashtags":{"$numberInt":"0"},"emocion_hilo_1":"Joy","tupla_emocion_hilo":"Joy+Anger","user_total_followers":{"$numberInt":"14132"},"user_puntaje_sigmo":{"$numberDouble":"1.04956"},"user_verificado":true,"log_prt":{"$numberDouble":"2.2624510897304293"},"log_pfv":{"$numberDouble":"2.89707700320942"},"log_total_retweets":{"$numberDouble":"3.3014640731433"},"log_total_favoritos":{"$numberDouble":"3.9380190974762104"},"rnd_user_puntaje_sigmo":{"$numberInt":"1"},"log_user_total_followers":{"$numberDouble":"4.1502343589578965"}}
{"_id":{"$oid":"5d34a67a6b361d34247c1e71"},"hilo":{"$numberInt":"154"},"topico":{"$numberInt":"11"},"total_tweets":{"$numberInt":"11"},"total_retweets":{"$numberInt":"10757"},"total_favoritos":{"$numberInt":"22748"},"promedio_rt":{"$numberInt":"978"},"promedio_fv":{"$numberInt":"2068"},"total_hashtags":{"$numberInt":"0"},"emocion_hilo_1":"Joy","tupla_emocion_hilo":"Joy+Sadness","user_total_followers":{"$numberInt":"31316"},"user_puntaje_sigmo":{"$numberDouble":"0.94618"},"user_verificado":false,"log_prt":{"$numberDouble":"2.9907826918031377"},"log_pfv":{"$numberDouble":"3.3157604906657347"},"log_total_retweets":{"$numberDouble":"4.0317315399458264"},"log_total_favoritos":{"$numberDouble":"4.356962310706225"},"rnd_user_puntaje_sigmo":{"$numberDouble":"0.9"},"log_user_total_followers":{"$numberDouble":"4.49578015230518"}}
{"_id":{"$oid":"5d34a67a6b361d34247c1e72"},"hilo":{"$numberInt":"156"},"topico":{"$numberInt":"2"},"total_tweets":{"$numberInt":"11"},"total_retweets":{"$numberInt":"4166"},"total_favoritos":{"$numberInt":"6435"},"promedio_rt":{"$numberInt":"379"},"promedio_fv":{"$numberInt":"585"},"total_hashtags":{"$numberInt":"0"},"emocion_hilo_1":"Anger","tupla_emocion_hilo":"Anger+Surprise","user_total_followers":{"$numberInt":"1031"},"user_puntaje_sigmo":{"$numberDouble":"0.76908"},"user_verificado":false,"log_prt":{"$numberDouble":"2.57978359661681"},"log_pfv":{"$numberDouble":"2.767897616018091"},"log_total_retweets":{"$numberDouble":"3.619823500457278"},"log_total_favoritos":{"$numberDouble":"3.808616035426992"},"rnd_user_puntaje_sigmo":{"$numberDouble":"0.8"},"log_user_total_followers":{"$numberDouble":"3.0136796972911926"}}
{"_id":{"$oid":"5d34a67a6b361d34247c1e73"},"hilo":{"$numberInt":"157"},"topico":{"$numberInt":"4"},"total_tweets":{"$numberInt":"11"},"total_retweets":{"$numberInt":"56"},"total_favoritos":{"$numberInt":"1509"},"promedio_rt":{"$numberInt":"5"},"promedio_fv":{"$numberInt":"137"},"total_hashtags":{"$numberInt":"4"},"emocion_hilo_1":"Joy","tupla_emocion_hilo":"Joy+Sadness","user_total_followers":{"$numberInt":"288"},"user_puntaje_sigmo":{"$numberDouble":"0.63758"},"user_verificado":false,"log_prt":{"$numberDouble":"0.7781512503836436"},"log_pfv":{"$numberDouble":"2.1398790864012365"},"log_total_retweets":{"$numberDouble":"1.7558748556724915"},"log_total_favoritos":{"$numberDouble":"3.1789769472931693"},"rnd_user_puntaje_sigmo":{"$numberDouble":"0.6"},"log_user_total_followers":{"$numberDouble":"2.4608978427565478"}}
{"_id":{"$oid":"5d34a67a6b361d34247c1e74"},"hilo":{"$numberInt":"159"},"topico":{"$numberInt":"0"},"total_tweets":{"$numberInt":"11"},"total_retweets":{"$numberInt":"188"},"total_favoritos":{"$numberInt":"1588"},"promedio_rt":{"$numberInt":"17"},"promedio_fv":{"$numberInt":"144"},"total_hashtags":{"$numberInt":"1"},"emocion_hilo_1":"Joy","tupla_emocion_hilo":"Joy+Surprise","user_total_followers":{"$numberInt":"23229"},"user_puntaje_sigmo":{"$numberDouble":"1.25513"},"user_verificado":false,"log_prt":{"$numberDouble":"1.255272505103306"},"log_pfv":{"$numberDouble":"2.161368002234975"},"log_total_retweets":{"$numberDouble":"2.2764618041732443"},"log_total_favoritos":{"$numberDouble":"3.2011238972073794"},"rnd_user_puntaje_sigmo":{"$numberDouble":"1.3"},"log_user_total_followers":{"$numberDouble":"4.366049209800235"}}
{"_id":{"$oid":"5d34a67a6b361d34247c1e75"},"hilo":{"$numberInt":"168"},"topico":{"$numberInt":"4"},"total_tweets":{"$numberInt":"12"},"total_retweets":{"$numberInt":"14001"},"total_favoritos":{"$numberInt":"35724"},"promedio_rt":{"$numberInt":"1167"},"promedio_fv":{"$numberInt":"2977"},"total_hashtags":{"$numberInt":"0"},"emocion_hilo_1":"Joy","tupla_emocion_hilo":"Joy+Surprise","user_total_followers":{"$numberInt":"84644"},"user_puntaje_sigmo":{"$numberDouble":"1.20034"},"user_verificado":false,"log_prt":{"$numberDouble":"3.0674428427763805"},"log_pfv":{"$numberDouble":"3.473924693416157"},"log_total_retweets":{"$numberDouble":"4.146190073315927"},"log_total_favoritos":{"$numberDouble":"4.552972237463008"},"rnd_user_puntaje_sigmo":{"$numberDouble":"1.2"},"log_user_total_followers":{"$numberDouble":"4.9276013093257225"}}
{"_id":{"$oid":"5d34a67a6b361d34247c1e76"},"hilo":{"$numberInt":"170"},"topico":{"$numberInt":"1"},"total_tweets":{"$numberInt":"12"},"total_retweets":{"$numberInt":"956"},"total_favoritos":{"$numberInt":"3532"},"promedio_rt":{"$numberInt":"80"},"promedio_fv":{"$numberInt":"294"},"total_hashtags":{"$numberInt":"0"},"emocion_hilo_1":"Joy","tupla_emocion_hilo":"Joy+Fear","user_total_followers":{"$numberInt":"4077"},"user_puntaje_sigmo":{"$numberDouble":"0.8902"},"user_verificado":false,"log_prt":{"$numberDouble":"1.9084850188786497"},"log_pfv":{"$numberDouble":"2.469822015978163"},"log_total_retweets":{"$numberDouble":"2.9809119377768436"},"log_total_favoritos":{"$numberDouble":"3.5481436374348454"},"rnd_user_puntaje_sigmo":{"$numberDouble":"0.9"},"log_user_total_followers":{"$numberDouble":"3.6104472214421213"}}
{"_id":{"$oid":"5d34a67a6b361d34247c1e77"},"hilo":{"$numberInt":"173"},"topico":{"$numberInt":"4"},"total_tweets":{"$numberInt":"12"},"total_retweets":{"$numberInt":"6693"},"total_favoritos":{"$numberInt":"15836"},"promedio_rt":{"$numberInt":"558"},"promedio_fv":{"$numberInt":"1320"},"total_hashtags":{"$numberInt":"0"},"emocion_hilo_1":"Fear","tupla_emocion_hilo":"Fear+Joy","user_total_followers":{"$numberInt":"132590"},"user_puntaje_sigmo":{"$numberDouble":"1.06386"},"user_verificado":false,"log_prt":{"$numberDouble":"2.747411807886423"},"log_pfv":{"$numberDouble":"3.1209028176145273"},"log_total_retweets":{"$numberDouble":"3.825685708021758"},"log_total_favoritos":{"$numberDouble":"4.199672916720621"},"rnd_user_puntaje_sigmo":{"$numberDouble":"1.1"},"log_user_total_followers":{"$numberDouble":"5.122514046067324"}}
{"_id":{"$oid":"5d34a67a6b361d34247c1e78"},"hilo":{"$numberInt":"176"},"topico":{"$numberInt":"4"},"total_tweets":{"$numberInt":"12"},"total_retweets":{"$numberInt":"990"},"total_favoritos":{"$numberInt":"4841"},"promedio_rt":{"$numberInt":"82"},"promedio_fv":{"$numberInt":"403"},"total_hashtags":{"$numberInt":"0"},"emocion_hilo_1":"Joy","tupla_emocion_hilo":"Joy+Fear","user_total_followers":{"$numberInt":"15505"},"user_puntaje_sigmo":{"$numberDouble":"0.95857"},"user_verificado":false,"log_prt":{"$numberDouble":"1.919078092376074"},"log_pfv":{"$numberDouble":"2.606381365110605"},"log_total_retweets":{"$numberDouble":"2.9960736544852753"},"log_total_favoritos":{"$numberDouble":"3.685024785105714"},"rnd_user_puntaje_sigmo":{"$numberInt":"1"},"log_user_total_followers":{"$numberDouble":"4.190499779633488"}}
{"_id":{"$oid":"5d34a67a6b361d34247c1e79"},"hilo":{"$numberInt":"186"},"topico":{"$numberInt":"11"},"total_tweets":{"$numberInt":"13"},"total_retweets":{"$numberInt":"22157"},"total_favoritos":{"$numberInt":"79276"},"promedio_rt":{"$numberInt":"1704"},"promedio_fv":{"$numberInt":"6098"},"total_hashtags":{"$numberInt":"0"},"emocion_hilo_1":"Joy","tupla_emocion_hilo":"Joy+Fear","user_total_followers":{"$numberInt":"756238"},"user_puntaje_sigmo":{"$numberDouble":"1.50679"},"user_verificado":true,"log_prt":{"$numberDouble":"3.2317243833285163"},"log_pfv":{"$numberDouble":"3.785258633357701"},"log_total_retweets":{"$numberDouble":"4.345530558034622"},"log_total_favoritos":{"$numberDouble":"4.899147207217667"},"rnd_user_puntaje_sigmo":{"$numberDouble":"1.5"},"log_user_total_followers":{"$numberDouble":"5.878659070603937"}}
{"_id":{"$oid":"5d34a67a6b361d34247c1e7a"},"hilo":{"$numberInt":"193"},"topico":{"$numberInt":"8"},"total_tweets":{"$numberInt":"13"},"total_retweets":{"$numberInt":"1632"},"total_favoritos":{"$numberInt":"8862"},"promedio_rt":{"$numberInt":"126"},"promedio_fv":{"$numberInt":"682"},"total_hashtags":{"$numberInt":"0"},"emocion_hilo_1":"Joy","tupla_emocion_hilo":"Joy+Fear","user_total_followers":{"$numberInt":"1257"},"user_puntaje_sigmo":{"$numberDouble":"0.87773"},"user_verificado":false,"log_prt":{"$numberDouble":"2.103803720955957"},"log_pfv":{"$numberDouble":"2.8344207036815328"},"log_total_retweets":{"$numberDouble":"3.212986184736668"},"log_total_favoritos":{"$numberDouble":"3.9475807493043225"},"rnd_user_puntaje_sigmo":{"$numberDouble":"0.9"},"log_user_total_followers":{"$numberDouble":"3.09968064110925"}}
{"_id":{"$oid":"5d34a67a6b361d34247c1e7b"},"hilo":{"$numberInt":"197"},"topico":{"$numberInt":"9"},"total_tweets":{"$numberInt":"13"},"total_retweets":{"$numberInt":"240786"},"total_favoritos":{"$numberInt":"952814"},"promedio_rt":{"$numberInt":"18522"},"promedio_fv":{"$numberInt":"73293"},"total_hashtags":{"$numberInt":"0"},"emocion_hilo_1":"Joy","tupla_emocion_hilo":"Joy+Anger","user_total_followers":{"$numberInt":"336166"},"user_puntaje_sigmo":{"$numberDouble":"1.16086"},"user_verificado":true,"log_prt":{"$numberDouble":"4.267711326726692"},"log_pfv":{"$numberDouble":"4.865068423842421"},"log_total_retweets":{"$numberDouble":"5.381633035822207"},"log_total_favoritos":{"$numberDouble":"5.979008585550655"},"rnd_user_puntaje_sigmo":{"$numberDouble":"1.2"},"log_user_total_followers":{"$numberDouble":"5.526555078463001"}}
{"_id":{"$oid":"5d34a67a6b361d34247c1e7c"},"hilo":{"$numberInt":"198"},"topico":{"$numberInt":"12"},"total_tweets":{"$numberInt":"13"},"total_retweets":{"$numberInt":"0"},"total_favoritos":{"$numberInt":"0"},"promedio_rt":{"$numberInt":"0"},"promedio_fv":{"$numberInt":"0"},"total_hashtags":{"$numberInt":"0"},"emocion_hilo_1":"Joy","tupla_emocion_hilo":"Joy+Fear","user_total_followers":{"$numberInt":"0"},"user_puntaje_sigmo":{"$numberInt":"0"},"user_verificado":false,"log_prt":{"$numberInt":"0"},"log_pfv":{"$numberInt":"0"},"log_total_retweets":{"$numberInt":"0"},"log_total_favoritos":{"$numberInt":"0"},"rnd_user_puntaje_sigmo":{"$numberInt":"0"},"log_user_total_followers":{"$numberInt":"0"}}
{"_id":{"$oid":"5d34a67a6b361d34247c1e7d"},"hilo":{"$numberInt":"200"},"topico":{"$numberInt":"4"},"total_tweets":{"$numberInt":"14"},"total_retweets":{"$numberInt":"35"},"total_favoritos":{"$numberInt":"100"},"promedio_rt":{"$numberInt":"2"},"promedio_fv":{"$numberInt":"7"},"total_hashtags":{"$numberInt":"0"},"emocion_hilo_1":"Joy","tupla_emocion_hilo":"Joy+Fear","user_total_followers":{"$numberInt":"45755"},"user_puntaje_sigmo":{"$numberDouble":"0.96577"},"user_verificado":true,"log_prt":{"$numberDouble":"0.47712125471966244"},"log_pfv":{"$numberDouble":"0.9030899869919435"},"log_total_retweets":{"$numberDouble":"1.5563025007672873"},"log_total_favoritos":{"$numberDouble":"2.0043213737826426"},"rnd_user_puntaje_sigmo":{"$numberInt":"1"},"log_user_total_followers":{"$numberDouble":"4.660448051321295"}}
{"_id":{"$oid":"5d34a67a6b361d34247c1e7e"},"hilo":{"$numberInt":"201"},"topico":{"$numberInt":"7"},"total_tweets":{"$numberInt":"14"},"total_retweets":{"$numberInt":"151"},"total_favoritos":{"$numberInt":"459"},"promedio_rt":{"$numberInt":"11"},"promedio_fv":{"$numberInt":"33"},"total_hashtags":{"$numberInt":"1"},"emocion_hilo_1":"Joy","tupla_emocion_hilo":"Joy+Anger","user_total_followers":{"$numberInt":"10751"},"user_puntaje_sigmo":{"$numberDouble":"0.91844"},"user_verificado":false,"log_prt":{"$numberDouble":"1.0791812460476249"},"log_pfv":{"$numberDouble":"1.5314789170422551"},"log_total_retweets":{"$numberDouble":"2.1818435879447726"},"log_total_favoritos":{"$numberDouble":"2.662757831681574"},"rnd_user_puntaje_sigmo":{"$numberDouble":"0.9"},"log_user_total_followers":{"$numberDouble":"4.03148925570975"}}
{"_id":{"$oid":"5d34a67a6b361d34247c1e7f"},"hilo":{"$numberInt":"202"},"topico":{"$numberInt":"11"},"total_tweets":{"$numberInt":"14"},"total_retweets":{"$numberInt":"1549"},"total_favoritos":{"$numberInt":"4618"},"promedio_rt":{"$numberInt":"111"},"promedio_fv":{"$numberInt":"330"},"total_hashtags":{"$numberInt":"1"},"emocion_hilo_1":"Fear","tupla_emocion_hilo":"Fear+Anger","user_total_followers":{"$numberInt":"72425"},"user_puntaje_sigmo":{"$numberDouble":"1.13011"},"user_verificado":false,"log_prt":{"$numberDouble":"2.0492180226701815"},"log_pfv":{"$numberDouble":"2.519827993775719"},"log_total_retweets":{"$numberDouble":"3.1903316981702914"},"log_total_favoritos":{"$numberDouble":"3.6645479622465467"},"rnd_user_puntaje_sigmo":{"$numberDouble":"1.1"},"log_user_total_followers":{"$numberDouble":"4.859894500306365"}}
{"_id":{"$oid":"5d34a67a6b361d34247c1e80"},"hilo":{"$numberInt":"210"},"topico":{"$numberInt":"12"},"total_tweets":{"$numberInt":"14"},"total_retweets":{"$numberInt":"18539"},"total_favoritos":{"$numberInt":"34069"},"promedio_rt":{"$numberInt":"1324"},"promedio_fv":{"$numberInt":"2434"},"total_hashtags":{"$numberInt":"0"},"emocion_hilo_1":"Joy","tupla_emocion_hilo":"Joy+Surprise","user_total_followers":{"$numberInt":"645393"},"user_puntaje_sigmo":{"$numberDouble":"1.24674"},"user_verificado":true,"log_prt":{"$numberDouble":"3.1222158782728267"},"log_pfv":{"$numberDouble":"3.386498965550653"},"log_total_retweets":{"$numberDouble":"4.2681097298084785"},"log_total_favoritos":{"$numberDouble":"4.532372133567877"},"rnd_user_puntaje_sigmo":{"$numberDouble":"1.2"},"log_user_total_followers":{"$numberDouble":"5.809824923604292"}}
{"_id":{"$oid":"5d34a67a6b361d34247c1e81"},"hilo":{"$numberInt":"214"},"topico":{"$numberInt":"7"},"total_tweets":{"$numberInt":"14"},"total_retweets":{"$numberInt":"6533"},"total_favoritos":{"$numberInt":"26756"},"promedio_rt":{"$numberInt":"467"},"promedio_fv":{"$numberInt":"1911"},"total_hashtags":{"$numberInt":"1"},"emocion_hilo_1":"Joy","tupla_emocion_hilo":"Joy+Surprise","user_total_followers":{"$numberInt":"80833"},"user_puntaje_sigmo":{"$numberDouble":"0.93907"},"user_verificado":true,"log_prt":{"$numberDouble":"2.670245853074124"},"log_pfv":{"$numberDouble":"3.2814878879400813"},"log_total_retweets":{"$numberDouble":"3.8151791301394185"},"log_total_favoritos":{"$numberDouble":"4.427437418644263"},"rnd_user_puntaje_sigmo":{"$numberDouble":"0.9"},"log_user_total_followers":{"$numberDouble":"4.90759407001401"}}
{"_id":{"$oid":"5d34a67a6b361d34247c1e82"},"hilo":{"$numberInt":"217"},"topico":{"$numberInt":"1"},"total_tweets":{"$numberInt":"14"},"total_retweets":{"$numberInt":"443"},"total_favoritos":{"$numberInt":"1918"},"promedio_rt":{"$numberInt":"32"},"promedio_fv":{"$numberInt":"137"},"total_hashtags":{"$numberInt":"0"},"emocion_hilo_1":"Fear","tupla_emocion_hilo":"Fear+Joy","user_total_followers":{"$numberInt":"9168"},"user_puntaje_sigmo":{"$numberDouble":"0.81963"},"user_verificado":false,"log_prt":{"$numberDouble":"1.5185139398778875"},"log_pfv":{"$numberDouble":"2.1398790864012365"},"log_total_retweets":{"$numberDouble":"2.6473829701146196"},"log_total_favoritos":{"$numberDouble":"3.2830749747354715"},"rnd_user_puntaje_sigmo":{"$numberDouble":"0.8"},"log_user_total_followers":{"$numberDouble":"3.9623219727295846"}}
{"_id":{"$oid":"5d34a67a6b361d34247c1e83"},"hilo":{"$numberInt":"221"},"topico":{"$numberInt":"11"},"total_tweets":{"$numberInt":"15"},"total_retweets":{"$numberInt":"24855"},"total_favoritos":{"$numberInt":"82796"},"promedio_rt":{"$numberInt":"1657"},"promedio_fv":{"$numberInt":"5520"},"total_hashtags":{"$numberInt":"1"},"emocion_hilo_1":"Anger","tupla_emocion_hilo":"Anger+Fear","user_total_followers":{"$numberInt":"458000"},"user_puntaje_sigmo":{"$numberDouble":"1.31484"},"user_verificado":true,"log_prt":{"$numberDouble":"3.2195845262142546"},"log_pfv":{"$numberDouble":"3.7420177471401384"},"log_total_retweets":{"$numberDouble":"4.395431240246918"},"log_total_favoritos":{"$numberDouble":"4.918014601192498"},"rnd_user_puntaje_sigmo":{"$numberDouble":"1.3"},"log_user_total_followers":{"$numberDouble":"5.660866426244061"}}
{"_id":{"$oid":"5d34a67a6b361d34247c1e84"},"hilo":{"$numberInt":"224"},"topico":{"$numberInt":"8"},"total_tweets":{"$numberInt":"15"},"total_retweets":{"$numberInt":"122"},"total_favoritos":{"$numberInt":"280"},"promedio_rt":{"$numberInt":"8"},"promedio_fv":{"$numberInt":"19"},"total_hashtags":{"$numberInt":"0"},"emocion_hilo_1":"Joy","tupla_emocion_hilo":"Joy+Fear","user_total_followers":{"$numberInt":"2462"},"user_puntaje_sigmo":{"$numberDouble":"0.79096"},"user_verificado":false,"log_prt":{"$numberDouble":"0.9542425094393249"},"log_pfv":{"$numberDouble":"1.3010299956639813"},"log_total_retweets":{"$numberDouble":"2.089905111439398"},"log_total_favoritos":{"$numberDouble":"2.44870631990508"},"rnd_user_puntaje_sigmo":{"$numberDouble":"0.8"},"log_user_total_followers":{"$numberDouble":"3.3914644118391033"}}
{"_id":{"$oid":"5d34a67a6b361d34247c1e85"},"hilo":{"$numberInt":"228"},"topico":{"$numberInt":"9"},"total_tweets":{"$numberInt":"15"},"total_retweets":{"$numberInt":"4969"},"total_favoritos":{"$numberInt":"9563"},"promedio_rt":{"$numberInt":"331"},"promedio_fv":{"$numberInt":"638"},"total_hashtags":{"$numberInt":"0"},"emocion_hilo_1":"Joy","tupla_emocion_hilo":"Joy+Fear","user_total_followers":{"$numberInt":"78135"},"user_puntaje_sigmo":{"$numberDouble":"1.63095"},"user_verificado":false,"log_prt":{"$numberDouble":"2.5211380837040362"},"log_pfv":{"$numberDouble":"2.8055008581584002"},"log_total_retweets":{"$numberDouble":"3.696356388733332"},"log_total_favoritos":{"$numberDouble":"3.9806395674437374"},"rnd_user_puntaje_sigmo":{"$numberDouble":"1.6"},"log_user_total_followers":{"$numberDouble":"4.892851174710722"}}
{"_id":{"$oid":"5d34a67a6b361d34247c1e86"},"hilo":{"$numberInt":"230"},"topico":{"$numberInt":"2"},"total_tweets":{"$numberInt":"15"},"total_retweets":{"$numberInt":"7555"},"total_favoritos":{"$numberInt":"49933"},"promedio_rt":{"$numberInt":"504"},"promedio_fv":{"$numberInt":"3329"},"total_hashtags":{"$numberInt":"0"},"emocion_hilo_1":"Sadness","tupla_emocion_hilo":"Sadness+Disgust","user_total_followers":{"$numberInt":"2614"},"user_puntaje_sigmo":{"$numberDouble":"0.87166"},"user_verificado":false,"log_prt":{"$numberDouble":"2.7032913781186614"},"log_pfv":{"$numberDouble":"3.5224442335063197"},"log_total_retweets":{"$numberDouble":"3.878291949249796"},"log_total_favoritos":{"$numberDouble":"4.698396356929269"},"rnd_user_puntaje_sigmo":{"$numberDouble":"0.9"},"log_user_total_followers":{"$numberDouble":"3.417471693203293"}}
{"_id":{"$oid":"5d34a67a6b361d34247c1e87"},"hilo":{"$numberInt":"239"},"topico":{"$numberInt":"12"},"total_tweets":{"$numberInt":"16"},"total_retweets":{"$numberInt":"1835"},"total_favoritos":{"$numberInt":"6526"},"promedio_rt":{"$numberInt":"115"},"promedio_fv":{"$numberInt":"408"},"total_hashtags":{"$numberInt":"1"},"emocion_hilo_1":"Joy","tupla_emocion_hilo":"Joy+Sadness","user_total_followers":{"$numberInt":"3660"},"user_puntaje_sigmo":{"$numberDouble":"0.7633"},"user_verificado":false,"log_prt":{"$numberDouble":"2.0644579892269186"},"log_pfv":{"$numberDouble":"2.611723308007342"},"log_total_retweets":{"$numberDouble":"3.2638726768652235"},"log_total_favoritos":{"$numberDouble":"3.814713612695977"},"rnd_user_puntaje_sigmo":{"$numberDouble":"0.8"},"log_user_total_followers":{"$numberDouble":"3.563599728881531"}}
{"_id":{"$oid":"5d34a67a6b361d34247c1e88"},"hilo":{"$numberInt":"246"},"topico":{"$numberInt":"5"},"total_tweets":{"$numberInt":"16"},"total_retweets":{"$numberInt":"4550"},"total_favoritos":{"$numberInt":"9238"},"promedio_rt":{"$numberInt":"284"},"promedio_fv":{"$numberInt":"577"},"total_hashtags":{"$numberInt":"0"},"emocion_hilo_1":"Joy","tupla_emocion_hilo":"Joy+Fear","user_total_followers":{"$numberInt":"51265"},"user_puntaje_sigmo":{"$numberDouble":"1.04661"},"user_verificado":false,"log_prt":{"$numberDouble":"2.45484486000851"},"log_pfv":{"$numberDouble":"2.761927838420529"},"log_total_retweets":{"$numberDouble":"3.658106835506393"},"log_total_favoritos":{"$numberDouble":"3.965624967109243"},"rnd_user_puntaje_sigmo":{"$numberInt":"1"},"log_user_total_followers":{"$numberDouble":"4.709829433186508"}}
{"_id":{"$oid":"5d34a67a6b361d34247c1e89"},"hilo":{"$numberInt":"255"},"topico":{"$numberInt":"7"},"total_tweets":{"$numberInt":"17"},"total_retweets":{"$numberInt":"2781"},"total_favoritos":{"$numberInt":"4806"},"promedio_rt":{"$numberInt":"164"},"promedio_fv":{"$numberInt":"283"},"total_hashtags":{"$numberInt":"36"},"emocion_hilo_1":"Joy","tupla_emocion_hilo":"Joy+Fear","user_total_followers":{"$numberInt":"1016"},"user_puntaje_sigmo":{"$numberDouble":"0.84309"},"user_verificado":false,"log_prt":{"$numberDouble":"2.2174839442139063"},"log_pfv":{"$numberDouble":"2.4533183400470375"},"log_total_retweets":{"$numberDouble":"3.4443571256560275"},"log_total_favoritos":{"$numberDouble":"3.681874122128647"},"rnd_user_puntaje_sigmo":{"$numberDouble":"0.8"},"log_user_total_followers":{"$numberDouble":"3.0073209529227447"}}
{"_id":{"$oid":"5d34a67a6b361d34247c1e8a"},"hilo":{"$numberInt":"260"},"topico":{"$numberInt":"4"},"total_tweets":{"$numberInt":"17"},"total_retweets":{"$numberInt":"308"},"total_favoritos":{"$numberInt":"627"},"promedio_rt":{"$numberInt":"18"},"promedio_fv":{"$numberInt":"37"},"total_hashtags":{"$numberInt":"3"},"emocion_hilo_1":"Joy","tupla_emocion_hilo":"Joy+Fear","user_total_followers":{"$numberInt":"35489"},"user_puntaje_sigmo":{"$numberDouble":"1.33976"},"user_verificado":false,"log_prt":{"$numberDouble":"1.2787536009528289"},"log_pfv":{"$numberDouble":"1.5797835966168101"},"log_total_retweets":{"$numberDouble":"2.4899584794248346"},"log_total_favoritos":{"$numberDouble":"2.797959643737196"},"rnd_user_puntaje_sigmo":{"$numberDouble":"1.3"},"log_user_total_followers":{"$numberDouble":"4.5501059993475925"}}
{"_id":{"$oid":"5d34a67a6b361d34247c1e8b"},"hilo":{"$numberInt":"263"},"topico":{"$numberInt":"4"},"total_tweets":{"$numberInt":"17"},"total_retweets":{"$numberInt":"4804"},"total_favoritos":{"$numberInt":"16870"},"promedio_rt":{"$numberInt":"283"},"promedio_fv":{"$numberInt":"992"},"total_hashtags":{"$numberInt":"0"},"emocion_hilo_1":"Fear","tupla_emocion_hilo":"Fear+Anger","user_total_followers":{"$numberInt":"73393"},"user_puntaje_sigmo":{"$numberDouble":"0.96141"},"user_verificado":true,"log_prt":{"$numberDouble":"2.4533183400470375"},"log_pfv":{"$numberDouble":"2.996949248495381"},"log_total_retweets":{"$numberDouble":"3.681693392004564"},"log_total_favoritos":{"$numberDouble":"4.227140825423186"},"rnd_user_puntaje_sigmo":{"$numberInt":"1"},"log_user_total_followers":{"$numberDouble":"4.8656605575536735"}}
{"_id":{"$oid":"5d34a67a6b361d34247c1e8c"},"hilo":{"$numberInt":"270"},"topico":{"$numberInt":"4"},"total_tweets":{"$numberInt":"18"},"total_retweets":{"$numberInt":"3954"},"total_favoritos":{"$numberInt":"15108"},"promedio_rt":{"$numberInt":"220"},"promedio_fv":{"$numberInt":"839"},"total_hashtags":{"$numberInt":"0"},"emocion_hilo_1":"Surprise","tupla_emocion_hilo":"Surprise+Fear","user_total_followers":{"$numberInt":"2500"},"user_puntaje_sigmo":{"$numberDouble":"0.94338"},"user_verificado":false,"log_prt":{"$numberDouble":"2.3443922736851106"},"log_pfv":{"$numberDouble":"2.9242792860618816"},"log_total_retweets":{"$numberDouble":"3.597146487833695"},"log_total_favoritos":{"$numberDouble":"4.179235721198481"},"rnd_user_puntaje_sigmo":{"$numberDouble":"0.9"},"log_user_total_followers":{"$numberDouble":"3.3981136917305026"}}
{"_id":{"$oid":"5d34a67a6b361d34247c1e8d"},"hilo":{"$numberInt":"272"},"topico":{"$numberInt":"5"},"total_tweets":{"$numberInt":"19"},"total_retweets":{"$numberInt":"4519"},"total_favoritos":{"$numberInt":"6939"},"promedio_rt":{"$numberInt":"238"},"promedio_fv":{"$numberInt":"365"},"total_hashtags":{"$numberInt":"0"},"emocion_hilo_1":"Joy","tupla_emocion_hilo":"Joy+Fear","user_total_followers":{"$numberInt":"51265"},"user_puntaje_sigmo":{"$numberDouble":"1.04661"},"user_verificado":false,"log_prt":{"$numberDouble":"2.3783979009481375"},"log_pfv":{"$numberDouble":"2.5634810853944106"},"log_total_retweets":{"$numberDouble":"3.655138434811382"},"log_total_favoritos":{"$numberDouble":"3.841359470454855"},"rnd_user_puntaje_sigmo":{"$numberInt":"1"},"log_user_total_followers":{"$numberDouble":"4.709829433186508"}}
{"_id":{"$oid":"5d34a67a6b361d34247c1e8e"},"hilo":{"$numberInt":"273"},"topico":{"$numberInt":"13"},"total_tweets":{"$numberInt":"19"},"total_retweets":{"$numberInt":"876"},"total_favoritos":{"$numberInt":"3001"},"promedio_rt":{"$numberInt":"46"},"promedio_fv":{"$numberInt":"158"},"total_hashtags":{"$numberInt":"0"},"emocion_hilo_1":"Surprise","tupla_emocion_hilo":"Surprise+Joy","user_total_followers":{"$numberInt":"9289"},"user_puntaje_sigmo":{"$numberDouble":"1.21805"},"user_verificado":false,"log_prt":{"$numberDouble":"1.6720978579357175"},"log_pfv":{"$numberDouble":"2.2013971243204513"},"log_total_retweets":{"$numberDouble":"2.9429995933660407"},"log_total_favoritos":{"$numberDouble":"3.4774106879072515"},"rnd_user_puntaje_sigmo":{"$numberDouble":"1.2"},"log_user_total_followers":{"$numberDouble":"3.968015713993642"}}
{"_id":{"$oid":"5d34a67a6b361d34247c1e8f"},"hilo":{"$numberInt":"275"},"topico":{"$numberInt":"1"},"total_tweets":{"$numberInt":"19"},"total_retweets":{"$numberInt":"54"},"total_favoritos":{"$numberInt":"234"},"promedio_rt":{"$numberInt":"3"},"promedio_fv":{"$numberInt":"12"},"total_hashtags":{"$numberInt":"0"},"emocion_hilo_1":"Joy","tupla_emocion_hilo":"Joy+Fear","user_total_followers":{"$numberInt":"37110"},"user_puntaje_sigmo":{"$numberDouble":"0.98445"},"user_verificado":false,"log_prt":{"$numberDouble":"0.6020599913279624"},"log_pfv":{"$numberDouble":"1.1139433523068367"},"log_total_retweets":{"$numberDouble":"1.7403626894942439"},"log_total_favoritos":{"$numberDouble":"2.3710678622717363"},"rnd_user_puntaje_sigmo":{"$numberInt":"1"},"log_user_total_followers":{"$numberDouble":"4.569502657087413"}}
{"_id":{"$oid":"5d34a67a6b361d34247c1e90"},"hilo":{"$numberInt":"277"},"topico":{"$numberInt":"4"},"total_tweets":{"$numberInt":"19"},"total_retweets":{"$numberInt":"2468"},"total_favoritos":{"$numberInt":"12310"},"promedio_rt":{"$numberInt":"130"},"promedio_fv":{"$numberInt":"648"},"total_hashtags":{"$numberInt":"0"},"emocion_hilo_1":"Joy","tupla_emocion_hilo":"Joy+Fear","user_total_followers":{"$numberInt":"7113"},"user_puntaje_sigmo":{"$numberDouble":"1.18423"},"user_verificado":false,"log_prt":{"$numberDouble":"2.1172712956557644"},"log_pfv":{"$numberDouble":"2.812244696800369"},"log_total_retweets":{"$numberDouble":"3.3925210899319325"},"log_total_favoritos":{"$numberDouble":"4.09029333131011"},"rnd_user_puntaje_sigmo":{"$numberDouble":"1.2"},"log_user_total_followers":{"$numberDouble":"3.8521138608497614"}}
{"_id":{"$oid":"5d34a67a6b361d34247c1e91"},"hilo":{"$numberInt":"280"},"topico":{"$numberInt":"4"},"total_tweets":{"$numberInt":"19"},"total_retweets":{"$numberInt":"11224"},"total_favoritos":{"$numberInt":"26070"},"promedio_rt":{"$numberInt":"591"},"promedio_fv":{"$numberInt":"1372"},"total_hashtags":{"$numberInt":"1"},"emocion_hilo_1":"Joy","tupla_emocion_hilo":"Joy+Fear","user_total_followers":{"$numberInt":"7380"},"user_puntaje_sigmo":{"$numberDouble":"0.81472"},"user_verificado":false,"log_prt":{"$numberDouble":"2.77232170672292"},"log_pfv":{"$numberDouble":"3.137670537236755"},"log_total_retweets":{"$numberDouble":"4.050186349675361"},"log_total_favoritos":{"$numberDouble":"4.416157689632185"},"rnd_user_puntaje_sigmo":{"$numberDouble":"0.8"},"log_user_total_followers":{"$numberDouble":"3.868115205327217"}}
{"_id":{"$oid":"5d34a67a6b361d34247c1e92"},"hilo":{"$numberInt":"286"},"topico":{"$numberInt":"1"},"total_tweets":{"$numberInt":"20"},"total_retweets":{"$numberInt":"1935"},"total_favoritos":{"$numberInt":"8190"},"promedio_rt":{"$numberInt":"97"},"promedio_fv":{"$numberInt":"410"},"total_hashtags":{"$numberInt":"0"},"emocion_hilo_1":"Joy","tupla_emocion_hilo":"Joy+Anger","user_total_followers":{"$numberInt":"6767"},"user_puntaje_sigmo":{"$numberDouble":"0.90308"},"user_verificado":false,"log_prt":{"$numberDouble":"1.9912260756924949"},"log_pfv":{"$numberDouble":"2.6138418218760693"},"log_total_retweets":{"$numberDouble":"3.286905352972375"},"log_total_favoritos":{"$numberDouble":"3.913336925932623"},"rnd_user_puntaje_sigmo":{"$numberDouble":"0.9"},"log_user_total_followers":{"$numberDouble":"3.8304603500309673"}}
{"_id":{"$oid":"5d34a67a6b361d34247c1e93"},"hilo":{"$numberInt":"292"},"topico":{"$numberInt":"1"},"total_tweets":{"$numberInt":"21"},"total_retweets":{"$numberInt":"2319"},"total_favoritos":{"$numberInt":"2883"},"promedio_rt":{"$numberInt":"110"},"promedio_fv":{"$numberInt":"137"},"total_hashtags":{"$numberInt":"0"},"emocion_hilo_1":"Fear","tupla_emocion_hilo":"Fear+Surprise","user_total_followers":{"$numberInt":"5525"},"user_puntaje_sigmo":{"$numberDouble":"0.8049"},"user_verificado":false,"log_prt":{"$numberDouble":"2.0453229787866576"},"log_pfv":{"$numberDouble":"2.1398790864012365"},"log_total_retweets":{"$numberDouble":"3.3654879848909"},"log_total_favoritos":{"$numberDouble":"3.4599952560473914"},"rnd_user_puntaje_sigmo":{"$numberDouble":"0.8"},"log_user_total_followers":{"$numberDouble":"3.7424108805804925"}}
{"_id":{"$oid":"5d34a67a6b361d34247c1e94"},"hilo":{"$numberInt":"298"},"topico":{"$numberInt":"4"},"total_tweets":{"$numberInt":"21"},"total_retweets":{"$numberInt":"3857"},"total_favoritos":{"$numberInt":"8601"},"promedio_rt":{"$numberInt":"184"},"promedio_fv":{"$numberInt":"410"},"total_hashtags":{"$numberInt":"0"},"emocion_hilo_1":"Joy","tupla_emocion_hilo":"Joy+Surprise","user_total_followers":{"$numberInt":"51265"},"user_puntaje_sigmo":{"$numberDouble":"1.04661"},"user_verificado":false,"log_prt":{"$numberDouble":"2.2671717284030137"},"log_pfv":{"$numberDouble":"2.6138418218760693"},"log_total_retweets":{"$numberDouble":"3.586362223307866"},"log_total_favoritos":{"$numberDouble":"3.934599438218073"},"rnd_user_puntaje_sigmo":{"$numberInt":"1"},"log_user_total_followers":{"$numberDouble":"4.709829433186508"}}
{"_id":{"$oid":"5d34a67a6b361d34247c1e95"},"hilo":{"$numberInt":"303"},"topico":{"$numberInt":"12"},"total_tweets":{"$numberInt":"21"},"total_retweets":{"$numberInt":"1783"},"total_favoritos":{"$numberInt":"3273"},"promedio_rt":{"$numberInt":"85"},"promedio_fv":{"$numberInt":"156"},"total_hashtags":{"$numberInt":"0"},"emocion_hilo_1":"Joy","tupla_emocion_hilo":"Joy+Anger","user_total_followers":{"$numberInt":"5489"},"user_puntaje_sigmo":{"$numberDouble":"1.05297"},"user_verificado":false,"log_prt":{"$numberDouble":"1.9344984512435677"},"log_pfv":{"$numberDouble":"2.1958996524092336"},"log_total_retweets":{"$numberDouble":"3.2513948500401044"},"log_total_favoritos":{"$numberDouble":"3.5150786750759226"},"rnd_user_puntaje_sigmo":{"$numberDouble":"1.1"},"log_user_total_followers":{"$numberDouble":"3.739572344450092"}}
{"_id":{"$oid":"5d34a67a6b361d34247c1e96"},"hilo":{"$numberInt":"306"},"topico":{"$numberInt":"6"},"total_tweets":{"$numberInt":"22"},"total_retweets":{"$numberInt":"211"},"total_favoritos":{"$numberInt":"451"},"promedio_rt":{"$numberInt":"10"},"promedio_fv":{"$numberInt":"20"},"total_hashtags":{"$numberInt":"0"},"emocion_hilo_1":"Joy","tupla_emocion_hilo":"Joy+Fear","user_total_followers":{"$numberInt":"12396"},"user_puntaje_sigmo":{"$numberDouble":"0.8396"},"user_verificado":false,"log_prt":{"$numberDouble":"1.0413926851582251"},"log_pfv":{"$numberDouble":"1.3222192947339193"},"log_total_retweets":{"$numberDouble":"2.326335860928751"},"log_total_favoritos":{"$numberDouble":"2.655138434811382"},"rnd_user_puntaje_sigmo":{"$numberDouble":"0.8"},"log_user_total_followers":{"$numberDouble":"4.093316601204331"}}
{"_id":{"$oid":"5d34a67a6b361d34247c1e97"},"hilo":{"$numberInt":"309"},"topico":{"$numberInt":"4"},"total_tweets":{"$numberInt":"22"},"total_retweets":{"$numberInt":"46127"},"total_favoritos":{"$numberInt":"307794"},"promedio_rt":{"$numberInt":"2097"},"promedio_fv":{"$numberInt":"13991"},"total_hashtags":{"$numberInt":"0"},"emocion_hilo_1":"Fear","tupla_emocion_hilo":"Fear+Joy","user_total_followers":{"$numberInt":"13334"},"user_puntaje_sigmo":{"$numberDouble":"1.03525"},"user_verificado":false,"log_prt":{"$numberDouble":"3.3218054838575393"},"log_pfv":{"$numberDouble":"4.14587979647062"},"log_total_retweets":{"$numberDouble":"4.663964625044133"},"log_total_favoritos":{"$numberDouble":"5.488261560622013"},"rnd_user_puntaje_sigmo":{"$numberInt":"1"},"log_user_total_followers":{"$numberDouble":"4.124993020025895"}}
{"_id":{"$oid":"5d34a67a6b361d34247c1e98"},"hilo":{"$numberInt":"310"},"topico":{"$numberInt":"4"},"total_tweets":{"$numberInt":"22"},"total_retweets":{"$numberInt":"79"},"total_favoritos":{"$numberInt":"530"},"promedio_rt":{"$numberInt":"4"},"promedio_fv":{"$numberInt":"24"},"total_hashtags":{"$numberInt":"4"},"emocion_hilo_1":"Joy","tupla_emocion_hilo":"Joy+Fear","user_total_followers":{"$numberInt":"52277"},"user_puntaje_sigmo":{"$numberDouble":"1.20736"},"user_verificado":true,"log_prt":{"$numberDouble":"0.6989700043360189"},"log_pfv":{"$numberDouble":"1.3979400086720377"},"log_total_retweets":{"$numberDouble":"1.9030899869919435"},"log_total_favoritos":{"$numberDouble":"2.725094521081469"},"rnd_user_puntaje_sigmo":{"$numberDouble":"1.2"},"log_user_total_followers":{"$numberDouble":"4.718318964417718"}}
{"_id":{"$oid":"5d34a67a6b361d34247c1e99"},"hilo":{"$numberInt":"313"},"topico":{"$numberInt":"9"},"total_tweets":{"$numberInt":"22"},"total_retweets":{"$numberInt":"9928"},"total_favoritos":{"$numberInt":"40662"},"promedio_rt":{"$numberInt":"451"},"promedio_fv":{"$numberInt":"1848"},"total_hashtags":{"$numberInt":"1"},"emocion_hilo_1":"Joy","tupla_emocion_hilo":"Joy+Fear","user_total_followers":{"$numberInt":"203698"},"user_puntaje_sigmo":{"$numberDouble":"1.32496"},"user_verificado":true,"log_prt":{"$numberDouble":"2.655138434811382"},"log_pfv":{"$numberDouble":"3.266936911159173"},"log_total_retweets":{"$numberDouble":"3.996905510695666"},"log_total_favoritos":{"$numberDouble":"4.609199416490486"},"rnd_user_puntaje_sigmo":{"$numberDouble":"1.3"},"log_user_total_followers":{"$numberDouble":"5.308988896965074"}}
{"_id":{"$oid":"5d34a67a6b361d34247c1e9a"},"hilo":{"$numberInt":"315"},"topico":{"$numberInt":"13"},"total_tweets":{"$numberInt":"23"},"total_retweets":{"$numberInt":"459"},"total_favoritos":{"$numberInt":"628"},"promedio_rt":{"$numberInt":"20"},"promedio_fv":{"$numberInt":"27"},"total_hashtags":{"$numberInt":"3"},"emocion_hilo_1":"Fear","tupla_emocion_hilo":"Fear+Joy","user_total_followers":{"$numberInt":"35489"},"user_puntaje_sigmo":{"$numberDouble":"1.33976"},"user_verificado":false,"log_prt":{"$numberDouble":"1.3222192947339193"},"log_pfv":{"$numberDouble":"1.4471580313422192"},"log_total_retweets":{"$numberDouble":"2.662757831681574"},"log_total_favoritos":{"$numberDouble":"2.798650645445269"},"rnd_user_puntaje_sigmo":{"$numberDouble":"1.3"},"log_user_total_followers":{"$numberDouble":"4.5501059993475925"}}
{"_id":{"$oid":"5d34a67a6b361d34247c1e9b"},"hilo":{"$numberInt":"317"},"topico":{"$numberInt":"8"},"total_tweets":{"$numberInt":"23"},"total_retweets":{"$numberInt":"610"},"total_favoritos":{"$numberInt":"895"},"promedio_rt":{"$numberInt":"27"},"promedio_fv":{"$numberInt":"39"},"total_hashtags":{"$numberInt":"3"},"emocion_hilo_1":"Anger","tupla_emocion_hilo":"Anger+Sadness","user_total_followers":{"$numberInt":"31234"},"user_puntaje_sigmo":{"$numberDouble":"0.81471"},"user_verificado":false,"log_prt":{"$numberDouble":"1.4471580313422192"},"log_pfv":{"$numberDouble":"1.6020599913279623"},"log_total_retweets":{"$numberDouble":"2.786041210242554"},"log_total_favoritos":{"$numberDouble":"2.9523080096621253"},"rnd_user_puntaje_sigmo":{"$numberDouble":"0.8"},"log_user_total_followers":{"$numberDouble":"4.49464151028204"}}
{"_id":{"$oid":"5d34a67a6b361d34247c1e9c"},"hilo":{"$numberInt":"319"},"topico":{"$numberInt":"10"},"total_tweets":{"$numberInt":"23"},"total_retweets":{"$numberInt":"1591"},"total_favoritos":{"$numberInt":"3550"},"promedio_rt":{"$numberInt":"69"},"promedio_fv":{"$numberInt":"154"},"total_hashtags":{"$numberInt":"1"},"emocion_hilo_1":"Joy","tupla_emocion_hilo":"Joy+Anger","user_total_followers":{"$numberInt":"29156"},"user_puntaje_sigmo":{"$numberDouble":"0.88945"},"user_verificado":false,"log_prt":{"$numberDouble":"1.845098040014257"},"log_pfv":{"$numberDouble":"2.1903316981702914"},"log_total_retweets":{"$numberDouble":"3.20194306340165"},"log_total_favoritos":{"$numberDouble":"3.5503506723016156"},"rnd_user_puntaje_sigmo":{"$numberDouble":"0.9"},"log_user_total_followers":{"$numberDouble":"4.464742836845146"}}
{"_id":{"$oid":"5d34a67a6b361d34247c1e9d"},"hilo":{"$numberInt":"321"},"topico":{"$numberInt":"9"},"total_tweets":{"$numberInt":"23"},"total_retweets":{"$numberInt":"102676"},"total_favoritos":{"$numberInt":"153219"},"promedio_rt":{"$numberInt":"4464"},"promedio_fv":{"$numberInt":"6662"},"total_hashtags":{"$numberInt":"4"},"emocion_hilo_1":"Joy","tupla_emocion_hilo":"Joy+Anger","user_total_followers":{"$numberInt":"434699"},"user_puntaje_sigmo":{"$numberDouble":"1.41566"},"user_verificado":true,"log_prt":{"$numberDouble":"3.649821463224565"},"log_pfv":{"$numberDouble":"3.8236698132681366"},"log_total_retweets":{"$numberDouble":"5.011473171038759"},"log_total_favoritos":{"$numberDouble":"5.1853154580036565"},"rnd_user_puntaje_sigmo":{"$numberDouble":"1.4"},"log_user_total_followers":{"$numberDouble":"5.638189640190837"}}
{"_id":{"$oid":"5d34a67a6b361d34247c1e9e"},"hilo":{"$numberInt":"324"},"topico":{"$numberInt":"4"},"total_tweets":{"$numberInt":"24"},"total_retweets":{"$numberInt":"2291"},"total_favoritos":{"$numberInt":"8221"},"promedio_rt":{"$numberInt":"95"},"promedio_fv":{"$numberInt":"343"},"total_hashtags":{"$numberInt":"0"},"emocion_hilo_1":"Joy","tupla_emocion_hilo":"Joy+Fear","user_total_followers":{"$numberInt":"132590"},"user_puntaje_sigmo":{"$numberDouble":"1.06386"},"user_verificado":false,"log_prt":{"$numberDouble":"1.9822712330395684"},"log_pfv":{"$numberDouble":"2.53655844257153"},"log_total_retweets":{"$numberDouble":"3.3602146132953523"},"log_total_favoritos":{"$numberDouble":"3.914977472444331"},"rnd_user_puntaje_sigmo":{"$numberDouble":"1.1"},"log_user_total_followers":{"$numberDouble":"5.122514046067324"}}
{"_id":{"$oid":"5d34a67a6b361d34247c1e9f"},"hilo":{"$numberInt":"331"},"topico":{"$numberInt":"4"},"total_tweets":{"$numberInt":"25"},"total_retweets":{"$numberInt":"6276"},"total_favoritos":{"$numberInt":"43273"},"promedio_rt":{"$numberInt":"251"},"promedio_fv":{"$numberInt":"1731"},"total_hashtags":{"$numberInt":"0"},"emocion_hilo_1":"Fear","tupla_emocion_hilo":"Fear+Anger","user_total_followers":{"$numberInt":"194060"},"user_puntaje_sigmo":{"$numberDouble":"1.31103"},"user_verificado":false,"log_prt":{"$numberDouble":"2.401400540781544"},"log_pfv":{"$numberDouble":"3.2385478876813276"},"log_total_retweets":{"$numberDouble":"3.7977521286507105"},"log_total_favoritos":{"$numberDouble":"4.636227040741543"},"rnd_user_puntaje_sigmo":{"$numberDouble":"1.3"},"log_user_total_followers":{"$numberDouble":"5.28793826497814"}}
{"_id":{"$oid":"5d34a67a6b361d34247c1ea0"},"hilo":{"$numberInt":"332"},"topico":{"$numberInt":"4"},"total_tweets":{"$numberInt":"25"},"total_retweets":{"$numberInt":"2"},"total_favoritos":{"$numberInt":"131"},"promedio_rt":{"$numberInt":"0"},"promedio_fv":{"$numberInt":"5"},"total_hashtags":{"$numberInt":"1"},"emocion_hilo_1":"Joy","tupla_emocion_hilo":"Joy+Fear","user_total_followers":{"$numberInt":"559"},"user_puntaje_sigmo":{"$numberDouble":"0.87525"},"user_verificado":false,"log_prt":{"$numberInt":"0"},"log_pfv":{"$numberDouble":"0.7781512503836436"},"log_total_retweets":{"$numberDouble":"0.47712125471966244"},"log_total_favoritos":{"$numberDouble":"2.12057393120585"},"rnd_user_puntaje_sigmo":{"$numberDouble":"0.9"},"log_user_total_followers":{"$numberDouble":"2.7481880270062002"}}
{"_id":{"$oid":"5d34a67a6b361d34247c1ea1"},"hilo":{"$numberInt":"336"},"topico":{"$numberInt":"4"},"total_tweets":{"$numberInt":"25"},"total_retweets":{"$numberInt":"27979"},"total_favoritos":{"$numberInt":"228020"},"promedio_rt":{"$numberInt":"1119"},"promedio_fv":{"$numberInt":"9121"},"total_hashtags":{"$numberInt":"0"},"emocion_hilo_1":"Fear","tupla_emocion_hilo":"Fear+Joy","user_total_followers":{"$numberInt":"124536"},"user_puntaje_sigmo":{"$numberDouble":"1.33038"},"user_verificado":true,"log_prt":{"$numberDouble":"3.0492180226701815"},"log_pfv":{"$numberDouble":"3.9600900679049196"},"log_total_retweets":{"$numberDouble":"4.446847710155809"},"log_total_favoritos":{"$numberDouble":"5.357974845965968"},"rnd_user_puntaje_sigmo":{"$numberDouble":"1.3"},"log_user_total_followers":{"$numberDouble":"5.095298399693248"}}
{"_id":{"$oid":"5d34a67a6b361d34247c1ea2"},"hilo":{"$numberInt":"337"},"topico":{"$numberInt":"6"},"total_tweets":{"$numberInt":"25"},"total_retweets":{"$numberInt":"341"},"total_favoritos":{"$numberInt":"1139"},"promedio_rt":{"$numberInt":"14"},"promedio_fv":{"$numberInt":"46"},"total_hashtags":{"$numberInt":"0"},"emocion_hilo_1":"Joy","tupla_emocion_hilo":"Joy+Surprise","user_total_followers":{"$numberInt":"2995"},"user_puntaje_sigmo":{"$numberDouble":"0.87645"},"user_verificado":false,"log_prt":{"$numberDouble":"1.1760912590556813"},"log_pfv":{"$numberDouble":"1.6720978579357175"},"log_total_retweets":{"$numberDouble":"2.534026106056135"},"log_total_favoritos":{"$numberDouble":"3.0569048513364727"},"rnd_user_puntaje_sigmo":{"$numberDouble":"0.9"},"log_user_total_followers":{"$numberDouble":"3.4765418090274287"}}
{"_id":{"$oid":"5d34a67a6b361d34247c1ea3"},"hilo":{"$numberInt":"340"},"topico":{"$numberInt":"6"},"total_tweets":{"$numberInt":"25"},"total_retweets":{"$numberInt":"51"},"total_favoritos":{"$numberInt":"493"},"promedio_rt":{"$numberInt":"2"},"promedio_fv":{"$numberInt":"20"},"total_hashtags":{"$numberInt":"8"},"emocion_hilo_1":"Joy","tupla_emocion_hilo":"Joy+Fear","user_total_followers":{"$numberInt":"3310"},"user_puntaje_sigmo":{"$numberDouble":"0.88331"},"user_verificado":false,"log_prt":{"$numberDouble":"0.47712125471966244"},"log_pfv":{"$numberDouble":"1.3222192947339193"},"log_total_retweets":{"$numberDouble":"1.7160033436347992"},"log_total_favoritos":{"$numberDouble":"2.693726948923647"},"rnd_user_puntaje_sigmo":{"$numberDouble":"0.9"},"log_user_total_followers":{"$numberDouble":"3.5199591807520685"}}
{"_id":{"$oid":"5d34a67a6b361d34247c1ea4"},"hilo":{"$numberInt":"341"},"topico":{"$numberInt":"3"},"total_tweets":{"$numberInt":"25"},"total_retweets":{"$numberInt":"8254"},"total_favoritos":{"$numberInt":"27677"},"promedio_rt":{"$numberInt":"330"},"promedio_fv":{"$numberInt":"1107"},"total_hashtags":{"$numberInt":"0"},"emocion_hilo_1":"Joy","tupla_emocion_hilo":"Joy+Fear","user_total_followers":{"$numberInt":"187007"},"user_puntaje_sigmo":{"$numberDouble":"0.90634"},"user_verificado":false,"log_prt":{"$numberDouble":"2.519827993775719"},"log_pfv":{"$numberDouble":"3.044539760392411"},"log_total_retweets":{"$numberDouble":"3.9167170775988125"},"log_total_favoritos":{"$numberDouble":"4.44213470499191"},"rnd_user_puntaje_sigmo":{"$numberDouble":"0.9"},"log_user_total_followers":{"$numberDouble":"5.271860185582165"}}
{"_id":{"$oid":"5d34a67a6b361d34247c1ea5"},"hilo":{"$numberInt":"342"},"topico":{"$numberInt":"9"},"total_tweets":{"$numberInt":"25"},"total_retweets":{"$numberInt":"135887"},"total_favoritos":{"$numberInt":"545596"},"promedio_rt":{"$numberInt":"5435"},"promedio_fv":{"$numberInt":"21824"},"total_hashtags":{"$numberInt":"0"},"emocion_hilo_1":"Joy","tupla_emocion_hilo":"Joy+Fear","user_total_followers":{"$numberInt":"336166"},"user_puntaje_sigmo":{"$numberDouble":"1.16086"},"user_verificado":true,"log_prt":{"$numberDouble":"3.7352794480604565"},"log_pfv":{"$numberDouble":"4.338954252377607"},"log_total_retweets":{"$numberDouble":"5.1331811067406905"},"log_total_favoritos":{"$numberDouble":"5.736871973659002"},"rnd_user_puntaje_sigmo":{"$numberDouble":"1.2"},"log_user_total_followers":{"$numberDouble":"5.526555078463001"}}
{"_id":{"$oid":"5d34a67a6b361d34247c1ea6"},"hilo":{"$numberInt":"343"},"topico":{"$numberInt":"8"},"total_tweets":{"$numberInt":"25"},"total_retweets":{"$numberInt":"389"},"total_favoritos":{"$numberInt":"3597"},"promedio_rt":{"$numberInt":"16"},"promedio_fv":{"$numberInt":"144"},"total_hashtags":{"$numberInt":"0"},"emocion_hilo_1":"Joy","tupla_emocion_hilo":"Joy+Surprise","user_total_followers":{"$numberInt":"11966"},"user_puntaje_sigmo":{"$numberDouble":"0.96127"},"user_verificado":false,"log_prt":{"$numberDouble":"1.2304489213782739"},"log_pfv":{"$numberDouble":"2.161368002234975"},"log_total_retweets":{"$numberDouble":"2.591064607026499"},"log_total_favoritos":{"$numberDouble":"3.5560611590095323"},"rnd_user_puntaje_sigmo":{"$numberInt":"1"},"log_user_total_followers":{"$numberDouble":"4.077985291029502"}}
{"_id":{"$oid":"5d34a67a6b361d34247c1ea7"},"hilo":{"$numberInt":"346"},"topico":{"$numberInt":"4"},"total_tweets":{"$numberInt":"26"},"total_retweets":{"$numberInt":"865"},"total_favoritos":{"$numberInt":"6287"},"promedio_rt":{"$numberInt":"33"},"promedio_fv":{"$numberInt":"242"},"total_hashtags":{"$numberInt":"0"},"emocion_hilo_1":"Fear","tupla_emocion_hilo":"Fear+Sadness","user_total_followers":{"$numberInt":"3499"},"user_puntaje_sigmo":{"$numberDouble":"1.00035"},"user_verificado":false,"log_prt":{"$numberDouble":"1.5314789170422551"},"log_pfv":{"$numberDouble":"2.385606273598312"},"log_total_retweets":{"$numberDouble":"2.937517892017347"},"log_total_favoritos":{"$numberDouble":"3.7985125330313516"},"rnd_user_puntaje_sigmo":{"$numberInt":"1"},"log_user_total_followers":{"$numberDouble":"3.5440680443502757"}}
{"_id":{"$oid":"5d34a67a6b361d34247c1ea8"},"hilo":{"$numberInt":"348"},"topico":{"$numberInt":"0"},"total_tweets":{"$numberInt":"26"},"total_retweets":{"$numberInt":"1947"},"total_favoritos":{"$numberInt":"5938"},"promedio_rt":{"$numberInt":"75"},"promedio_fv":{"$numberInt":"228"},"total_hashtags":{"$numberInt":"0"},"emocion_hilo_1":"Fear","tupla_emocion_hilo":"Fear+Sadness","user_total_followers":{"$numberInt":"4086"},"user_puntaje_sigmo":{"$numberDouble":"0.82257"},"user_verificado":false,"log_prt":{"$numberDouble":"1.8808135922807914"},"log_pfv":{"$numberDouble":"2.359835482339888"},"log_total_retweets":{"$numberDouble":"3.2895889525425965"},"log_total_favoritos":{"$numberDouble":"3.7737133252770216"},"rnd_user_puntaje_sigmo":{"$numberDouble":"0.8"},"log_user_total_followers":{"$numberDouble":"3.6114046377115936"}}
{"_id":{"$oid":"5d34a67a6b361d34247c1ea9"},"hilo":{"$numberInt":"350"},"topico":{"$numberInt":"13"},"total_tweets":{"$numberInt":"26"},"total_retweets":{"$numberInt":"547"},"total_favoritos":{"$numberInt":"608"},"promedio_rt":{"$numberInt":"21"},"promedio_fv":{"$numberInt":"23"},"total_hashtags":{"$numberInt":"2"},"emocion_hilo_1":"Joy","tupla_emocion_hilo":"Joy+Fear","user_total_followers":{"$numberInt":"35489"},"user_puntaje_sigmo":{"$numberDouble":"1.33976"},"user_verificado":false,"log_prt":{"$numberDouble":"1.3424226808222062"},"log_pfv":{"$numberDouble":"1.380211241711606"},"log_total_retweets":{"$numberDouble":"2.738780558484369"},"log_total_favoritos":{"$numberDouble":"2.784617292632875"},"rnd_user_puntaje_sigmo":{"$numberDouble":"1.3"},"log_user_total_followers":{"$numberDouble":"4.5501059993475925"}}
{"_id":{"$oid":"5d34a67a6b361d34247c1eaa"},"hilo":{"$numberInt":"351"},"topico":{"$numberInt":"4"},"total_tweets":{"$numberInt":"26"},"total_retweets":{"$numberInt":"3486"},"total_favoritos":{"$numberInt":"11057"},"promedio_rt":{"$numberInt":"134"},"promedio_fv":{"$numberInt":"425"},"total_hashtags":{"$numberInt":"0"},"emocion_hilo_1":"Joy","tupla_emocion_hilo":"Joy+Fear","user_total_followers":{"$numberInt":"132590"},"user_puntaje_sigmo":{"$numberDouble":"1.06386"},"user_verificado":false,"log_prt":{"$numberDouble":"2.130333768495006"},"log_pfv":{"$numberDouble":"2.629409599102719"},"log_total_retweets":{"$numberDouble":"3.5424519473759766"},"log_total_favoritos":{"$numberDouble":"4.043676585602717"},"rnd_user_puntaje_sigmo":{"$numberDouble":"1.1"},"log_user_total_followers":{"$numberDouble":"5.122514046067324"}}
{"_id":{"$oid":"5d34a67a6b361d34247c1eab"},"hilo":{"$numberInt":"353"},"topico":{"$numberInt":"9"},"total_tweets":{"$numberInt":"26"},"total_retweets":{"$numberInt":"3113"},"total_favoritos":{"$numberInt":"5840"},"promedio_rt":{"$numberInt":"120"},"promedio_fv":{"$numberInt":"225"},"total_hashtags":{"$numberInt":"6"},"emocion_hilo_1":"Fear","tupla_emocion_hilo":"Fear+Joy","user_total_followers":{"$numberInt":"35255"},"user_puntaje_sigmo":{"$numberDouble":"1.22232"},"user_verificado":false,"log_prt":{"$numberDouble":"2.0827853703164503"},"log_pfv":{"$numberDouble":"2.3541084391474008"},"log_total_retweets":{"$numberDouble":"3.4933186082321015"},"log_total_favoritos":{"$numberDouble":"3.766487206239694"},"rnd_user_puntaje_sigmo":{"$numberDouble":"1.2"},"log_user_total_followers":{"$numberDouble":"4.547233037501862"}}
{"_id":{"$oid":"5d34a67a6b361d34247c1eac"},"hilo":{"$numberInt":"354"},"topico":{"$numberInt":"7"},"total_tweets":{"$numberInt":"27"},"total_retweets":{"$numberInt":"844"},"total_favoritos":{"$numberInt":"2117"},"promedio_rt":{"$numberInt":"31"},"promedio_fv":{"$numberInt":"78"},"total_hashtags":{"$numberInt":"0"},"emocion_hilo_1":"Joy","tupla_emocion_hilo":"Joy+Sadness","user_total_followers":{"$numberInt":"12396"},"user_puntaje_sigmo":{"$numberDouble":"0.8396"},"user_verificado":false,"log_prt":{"$numberDouble":"1.505149978319906"},"log_pfv":{"$numberDouble":"1.8976270912904414"},"log_total_retweets":{"$numberDouble":"2.926856708949692"},"log_total_favoritos":{"$numberDouble":"3.325925955771466"},"rnd_user_puntaje_sigmo":{"$numberDouble":"0.8"},"log_user_total_followers":{"$numberDouble":"4.093316601204331"}}
{"_id":{"$oid":"5d34a67a6b361d34247c1ead"},"hilo":{"$numberInt":"360"},"topico":{"$numberInt":"5"},"total_tweets":{"$numberInt":"28"},"total_retweets":{"$numberInt":"20661"},"total_favoritos":{"$numberInt":"41698"},"promedio_rt":{"$numberInt":"738"},"promedio_fv":{"$numberInt":"1489"},"total_hashtags":{"$numberInt":"0"},"emocion_hilo_1":"Joy","tupla_emocion_hilo":"Joy+Fear","user_total_followers":{"$numberInt":"125031"},"user_puntaje_sigmo":{"$numberDouble":"1.27649"},"user_verificado":false,"log_prt":{"$numberDouble":"2.8686444383948255"},"log_pfv":{"$numberDouble":"3.173186268412274"},"log_total_retweets":{"$numberDouble":"4.315172357208987"},"log_total_favoritos":{"$numberDouble":"4.620125640113102"},"rnd_user_puntaje_sigmo":{"$numberDouble":"1.3"},"log_user_total_followers":{"$numberDouble":"5.09702117816689"}}
{"_id":{"$oid":"5d34a67a6b361d34247c1eae"},"hilo":{"$numberInt":"365"},"topico":{"$numberInt":"5"},"total_tweets":{"$numberInt":"29"},"total_retweets":{"$numberInt":"2818"},"total_favoritos":{"$numberInt":"4979"},"promedio_rt":{"$numberInt":"97"},"promedio_fv":{"$numberInt":"172"},"total_hashtags":{"$numberInt":"0"},"emocion_hilo_1":"Fear","tupla_emocion_hilo":"Fear+Disgust","user_total_followers":{"$numberInt":"51265"},"user_puntaje_sigmo":{"$numberDouble":"1.04661"},"user_verificado":false,"log_prt":{"$numberDouble":"1.9912260756924949"},"log_pfv":{"$numberDouble":"2.2380461031287955"},"log_total_retweets":{"$numberDouble":"3.4500950758716025"},"log_total_favoritos":{"$numberDouble":"3.6972293427597176"},"rnd_user_puntaje_sigmo":{"$numberInt":"1"},"log_user_total_followers":{"$numberDouble":"4.709829433186508"}}
{"_id":{"$oid":"5d34a67a6b361d34247c1eaf"},"hilo":{"$numberInt":"367"},"topico":{"$numberInt":"1"},"total_tweets":{"$numberInt":"30"},"total_retweets":{"$numberInt":"163"},"total_favoritos":{"$numberInt":"1483"},"promedio_rt":{"$numberInt":"5"},"promedio_fv":{"$numberInt":"49"},"total_hashtags":{"$numberInt":"0"},"emocion_hilo_1":"Joy","tupla_emocion_hilo":"Joy+Fear","user_total_followers":{"$numberInt":"8407"},"user_puntaje_sigmo":{"$numberDouble":"0.88689"},"user_verificado":false,"log_prt":{"$numberDouble":"0.7781512503836436"},"log_pfv":{"$numberDouble":"1.6989700043360187"},"log_total_retweets":{"$numberDouble":"2.214843848047698"},"log_total_favoritos":{"$numberDouble":"3.171433900943008"},"rnd_user_puntaje_sigmo":{"$numberDouble":"0.9"},"log_user_total_followers":{"$numberDouble":"3.924692703020186"}}
{"_id":{"$oid":"5d34a67a6b361d34247c1eb0"},"hilo":{"$numberInt":"373"},"topico":{"$numberInt":"7"},"total_tweets":{"$numberInt":"32"},"total_retweets":{"$numberInt":"1979"},"total_favoritos":{"$numberInt":"3153"},"promedio_rt":{"$numberInt":"62"},"promedio_fv":{"$numberInt":"99"},"total_hashtags":{"$numberInt":"4"},"emocion_hilo_1":"Joy","tupla_emocion_hilo":"Joy+Fear","user_total_followers":{"$numberInt":"63802"},"user_puntaje_sigmo":{"$numberDouble":"0.84982"},"user_verificado":false,"log_prt":{"$numberDouble":"1.7993405494535817"},"log_pfv":{"$numberInt":"2"},"log_total_retweets":{"$numberDouble":"3.296665190261531"},"log_total_favoritos":{"$numberDouble":"3.498861688992884"},"rnd_user_puntaje_sigmo":{"$numberDouble":"0.8"},"log_user_total_followers":{"$numberDouble":"4.804841099611673"}}
{"_id":{"$oid":"5d34a67a6b361d34247c1eb1"},"hilo":{"$numberInt":"375"},"topico":{"$numberInt":"7"},"total_tweets":{"$numberInt":"33"},"total_retweets":{"$numberInt":"4114"},"total_favoritos":{"$numberInt":"5935"},"promedio_rt":{"$numberInt":"125"},"promedio_fv":{"$numberInt":"180"},"total_hashtags":{"$numberInt":"0"},"emocion_hilo_1":"Joy","tupla_emocion_hilo":"Joy+Surprise","user_total_followers":{"$numberInt":"59435"},"user_puntaje_sigmo":{"$numberDouble":"1.09865"},"user_verificado":true,"log_prt":{"$numberDouble":"2.100370545117563"},"log_pfv":{"$numberDouble":"2.2576785748691846"},"log_total_retweets":{"$numberDouble":"3.6143698395482886"},"log_total_favoritos":{"$numberDouble":"3.7734938922709707"},"rnd_user_puntaje_sigmo":{"$numberDouble":"1.1"},"log_user_total_followers":{"$numberDouble":"4.774049574030081"}}
{"_id":{"$oid":"5d34a67a6b361d34247c1eb2"},"hilo":{"$numberInt":"376"},"topico":{"$numberInt":"7"},"total_tweets":{"$numberInt":"33"},"total_retweets":{"$numberInt":"4101"},"total_favoritos":{"$numberInt":"7948"},"promedio_rt":{"$numberInt":"124"},"promedio_fv":{"$numberInt":"241"},"total_hashtags":{"$numberInt":"0"},"emocion_hilo_1":"Joy","tupla_emocion_hilo":"Joy+Fear","user_total_followers":{"$numberInt":"38232"},"user_puntaje_sigmo":{"$numberDouble":"1.30939"},"user_verificado":false,"log_prt":{"$numberDouble":"2.0969100130080562"},"log_pfv":{"$numberDouble":"2.383815365980431"},"log_total_retweets":{"$numberDouble":"3.6129956560323473"},"log_total_favoritos":{"$numberDouble":"3.9003124969837266"},"rnd_user_puntaje_sigmo":{"$numberDouble":"1.3"},"log_user_total_followers":{"$numberDouble":"4.582438376813906"}}
{"_id":{"$oid":"5d34a67a6b361d34247c1eb3"},"hilo":{"$numberInt":"385"},"topico":{"$numberInt":"5"},"total_tweets":{"$numberInt":"38"},"total_retweets":{"$numberInt":"14899"},"total_favoritos":{"$numberInt":"26196"},"promedio_rt":{"$numberInt":"392"},"promedio_fv":{"$numberInt":"689"},"total_hashtags":{"$numberInt":"2"},"emocion_hilo_1":"Surprise","tupla_emocion_hilo":"Surprise+Fear","user_total_followers":{"$numberInt":"133721"},"user_puntaje_sigmo":{"$numberDouble":"0.99404"},"user_verificado":false,"log_prt":{"$numberDouble":"2.5943925503754266"},"log_pfv":{"$numberDouble":"2.838849090737255"},"log_total_retweets":{"$numberDouble":"4.173186268412274"},"log_total_favoritos":{"$numberDouble":"4.418251560096693"},"rnd_user_puntaje_sigmo":{"$numberInt":"1"},"log_user_total_followers":{"$numberDouble":"5.126202863452002"}}
{"_id":{"$oid":"5d34a67a6b361d34247c1eb4"},"hilo":{"$numberInt":"387"},"topico":{"$numberInt":"6"},"total_tweets":{"$numberInt":"39"},"total_retweets":{"$numberInt":"214"},"total_favoritos":{"$numberInt":"1581"},"promedio_rt":{"$numberInt":"5"},"promedio_fv":{"$numberInt":"41"},"total_hashtags":{"$numberInt":"0"},"emocion_hilo_1":"Surprise","tupla_emocion_hilo":"Surprise+Fear","user_total_followers":{"$numberInt":"40252"},"user_puntaje_sigmo":{"$numberDouble":"1.01661"},"user_verificado":false,"log_prt":{"$numberDouble":"0.7781512503836436"},"log_pfv":{"$numberDouble":"1.6232492903979006"},"log_total_retweets":{"$numberDouble":"2.3324384599156054"},"log_total_favoritos":{"$numberDouble":"3.1992064791616577"},"rnd_user_puntaje_sigmo":{"$numberInt":"1"},"log_user_total_followers":{"$numberDouble":"4.604798253272669"}}
{"_id":{"$oid":"5d34a67a6b361d34247c1eb5"},"hilo":{"$numberInt":"389"},"topico":{"$numberInt":"4"},"total_tweets":{"$numberInt":"40"},"total_retweets":{"$numberInt":"70517"},"total_favoritos":{"$numberInt":"312186"},"promedio_rt":{"$numberInt":"1763"},"promedio_fv":{"$numberInt":"7805"},"total_hashtags":{"$numberInt":"0"},"emocion_hilo_1":"Joy","tupla_emocion_hilo":"Joy+Surprise","user_total_followers":{"$numberInt":"646121"},"user_puntaje_sigmo":{"$numberDouble":"1.51784"},"user_verificado":false,"log_prt":{"$numberDouble":"3.246498580795801"},"log_pfv":{"$numberDouble":"3.8924285469452298"},"log_total_retweets":{"$numberDouble":"4.848299986535949"},"log_total_favoritos":{"$numberDouble":"5.494414814338781"},"rnd_user_puntaje_sigmo":{"$numberDouble":"1.5"},"log_user_total_followers":{"$numberDouble":"5.810314528713808"}}
{"_id":{"$oid":"5d34a67a6b361d34247c1eb6"},"hilo":{"$numberInt":"390"},"topico":{"$numberInt":"4"},"total_tweets":{"$numberInt":"41"},"total_retweets":{"$numberInt":"53838"},"total_favoritos":{"$numberInt":"137137"},"promedio_rt":{"$numberInt":"1313"},"promedio_fv":{"$numberInt":"3345"},"total_hashtags":{"$numberInt":"0"},"emocion_hilo_1":"Fear","tupla_emocion_hilo":"Fear+Sadness","user_total_followers":{"$numberInt":"38577"},"user_puntaje_sigmo":{"$numberDouble":"1.17787"},"user_verificado":false,"log_prt":{"$numberDouble":"3.118595365223762"},"log_pfv":{"$numberDouble":"3.5245259366263757"},"log_total_retweets":{"$numberDouble":"4.731096984750186"},"log_total_favoritos":{"$numberDouble":"5.137157811490028"},"rnd_user_puntaje_sigmo":{"$numberDouble":"1.2"},"log_user_total_followers":{"$numberDouble":"4.586339708754249"}}
