<?xml version="1.0" encoding="UTF-8" ?><root><hilo type="int">55</hilo><total_tweets type="int">6</total_tweets><texto type="str">💬 Do you think #threads can help make Twitter healthier? Yesterday, @jack answered our question on Periscope 👇 #health #twitter https://t.co/AHE0xOvtTT 
 « I do think the more space we give people to think and be critical about what they see and express more critical thinking the more civil and civic these dialogs and debates become and the more we can really dive into the heart of the issue and move forward. » 
 « 280 and Threads have certainly allowed more depth in the conversations and a lot more critical thinking. One of the things we would like to see and enable on our platform is exactly that. » 
 « We do believe it has a potential but we don’t know and that’s part of the point. […] We haven’t figured out how to measure the effect of that on our platform. » 
 « This is a step in first admitting that we don’t know how to measure that, second like, to do find the measurements and third to make sure we are exposing what we’re measuring and sharing that and evolving it as quickly as we can. » 
 See when @jack answers our question or just watch the replay about Twitter&apos;s #health 👇 https://t.co/QRv370qiFB</texto><total_retweets type="int">2</total_retweets><total_favoritos type="int">10</total_favoritos><total_replies type="int">7</total_replies><total_hashtags type="int">3</total_hashtags><emocion_max_1 type="str">Joy</emocion_max_1><emocion_max_2 type="str">Fear</emocion_max_2><emocion_moda_1 type="str">Joy</emocion_moda_1><emocion_moda_2 type="str">Surprise</emocion_moda_2><emocion_media_1 type="str">Joy</emocion_media_1><emocion_media_2 type="str">Fear</emocion_media_2><emocion_presente_1 type="str">Joy</emocion_presente_1><emocion_presente_2 type="str">Surprise</emocion_presente_2><usuario type="number">900271822465380352</usuario><user_total_followers type="int">9786</user_total_followers><user_total_friends type="int">892</user_total_friends><user_total_status type="int">18550</user_total_status><user_puntaje_sigmo type="float">1.010073304411577</user_puntaje_sigmo><user_verificado type="bool">False</user_verificado></root>